{"id": "7452522186927066410", "formats": [{"ext": "mp4", "vcodec": "h264", "acodec": "aac", "format_id": "h264_540p_314476-0", "tbr": 314, "quality": 1, "preference": -1, "filesize": 2205267, "width": 576, "height": 1024, "url": "https://v16-webapp-prime.us.tiktok.com/video/tos/useast5/tos-useast5-ve-0068c003-tx/okiyaCYUZEttr4SxAEBVihlEGQBiv2ssnsgyI/?a=1988&bti=ODszNWYuMDE6&&bt=307&ft=4KJMyMzm8Zmo0yzRFa4jVBnodpWrKsd.&mime_type=video_mp4&rc=aDQ6Ozg1aDhlaGhlZTc4ZEBpM29kZWw5cjdkdzMzZzczNEBjLy9jXjU2NV8xMTFiX15jYSNqbmA2MmRrbGpgLS1kMS9zcw%3D%3D&expire=1779007689&l=202605150847137780C96EA93873025E7D&ply_type=2&policy=2&signature=4f08d67404d65186ee585400cfafb3fc&tk=tt_chain_token&btag=e00088000", "protocol": "https", "video_ext": "mp4", "audio_ext": "none", "resolution": "576x1024", "dynamic_range": "SDR", "aspect_ratio": 0.56, "cookies": "ttwid=1%7CGDhFJwSAscwdaQsU5eawTziZsZ-W33086-T8iT4lhh4%7C1778834833%7C915a7b7731c4d546832c9d6cf9c6eda71497c6e171561813f6a5de6045b84757; Domain=.tiktok.com; Path=/; Secure; Expires=1809938833; tt_csrf_token=mVAY7ZEb-31BTYT0TT2DtZu5AsDSsvBjC9kg; Domain=.tiktok.com; Path=/; Secure; tt_chain_token=\"rLj6efEsYd5gdm8VRZAFaw==\"; Domain=.tiktok.com; Path=/; Secure; Expires=1794386833", "http_headers": {"User-Agent": "Mozilla/5.0 (Windows NT 10.0; Win64; x64) AppleWebKit/537.36 (KHTML, like Gecko) Chrome/143.0.0.0 Safari/537.36", "Accept": "text/html,application/xhtml+xml,application/xml;q=0.9,*/*;q=0.8", "Accept-Language": "en-us,en;q=0.5", "Sec-Fetch-Mode": "navigate", "Referer": "https://www.tiktok.com/@badgirlwyntaaaa/video/7452522186927066410"}, "format": "h264_540p_314476-0 - 576x1024"}, {"ext": "mp4", "vcodec": "h264", "acodec": "aac", "format_id": "h264_540p_314476-1", "tbr": 314, "quality": 1, "preference": -1, "filesize": 2205267, "width": 576, "height": 1024, "url": "https://v19-webapp-prime.us.tiktok.com/video/tos/useast5/tos-useast5-ve-0068c003-tx/okiyaCYUZEttr4SxAEBVihlEGQBiv2ssnsgyI/?a=1988&bti=ODszNWYuMDE6&&bt=307&ft=4KJMyMzm8Zmo0yzRFa4jVBnodpWrKsd.&mime_type=video_mp4&rc=aDQ6Ozg1aDhlaGhlZTc4ZEBpM29kZWw5cjdkdzMzZzczNEBjLy9jXjU2NV8xMTFiX15jYSNqbmA2MmRrbGpgLS1kMS9zcw%3D%3D&expire=1779007689&l=202605150847137780C96EA93873025E7D&ply_type=2&policy=2&signature=4f08d67404d65186ee585400cfafb3fc&tk=tt_chain_token&btag=e00088000", "protocol": "https", "video_ext": "mp4", "audio_ext": "none", "resolution": "576x1024", "dynamic_range": "SDR", "aspect_ratio": 0.56, "cookies": "ttwid=1%7CGDhFJwSAscwdaQsU5eawTziZsZ-W33086-T8iT4lhh4%7C1778834833%7C915a7b7731c4d546832c9d6cf9c6eda71497c6e171561813f6a5de6045b84757; Domain=.tiktok.com; Path=/; Secure; Expires=1809938833; tt_csrf_token=mVAY7ZEb-31BTYT0TT2DtZu5AsDSsvBjC9kg; Domain=.tiktok.com; Path=/; Secure; tt_chain_token=\"rLj6efEsYd5gdm8VRZAFaw==\"; Domain=.tiktok.com; Path=/; Secure; Expires=1794386833", "http_headers": {"User-Agent": "Mozilla/5.0 (Windows NT 10.0; Win64; x64) AppleWebKit/537.36 (KHTML, like Gecko) Chrome/143.0.0.0 Safari/537.36", "Accept": "text/html,application/xhtml+xml,application/xml;q=0.9,*/*;q=0.8", "Accept-Language": "en-us,en;q=0.5", "Sec-Fetch-Mode": "navigate", "Referer": "https://www.tiktok.com/@badgirlwyntaaaa/video/7452522186927066410"}, "format": "h264_540p_314476-1 - 576x1024"}, {"ext": "mp4", "vcodec": "h264", "acodec": "aac", "format_id": "h264_540p_789650-0", "tbr": 789, "quality": 1, "preference": -1, "filesize": 5537423, "width": 576, "height": 1024, "url": "https://v16-webapp-prime.us.tiktok.com/video/tos/useast5/tos-useast5-pve-0068-tx/oAYw6gSDnBWkreaFEKjKwAQlEDFZfbKgbRIw7S/?a=1988&bti=ODszNWYuMDE6&&bt=771&ft=4KJMyMzm8Zmo0yzRFa4jVBnodpWrKsd.&mime_type=video_mp4&rc=OjRkZjs4NjhpZGQ6NjtmOEBpM29kZWw5cjdkdzMzZzczNEA1X2JgYTFhXzExMmA2NGNjYSNqbmA2MmRrbGpgLS1kMS9zcw%3D%3D&expire=1779007689&l=202605150847137780C96EA93873025E7D&ply_type=2&policy=2&signature=fe0148ba15038390f58841f79f1ef194&tk=tt_chain_token&btag=e00088000", "protocol": "https", "video_ext": "mp4", "audio_ext": "none", "resolution": "576x1024", "dynamic_range": "SDR", "aspect_ratio": 0.56, "cookies": "ttwid=1%7CGDhFJwSAscwdaQsU5eawTziZsZ-W33086-T8iT4lhh4%7C1778834833%7C915a7b7731c4d546832c9d6cf9c6eda71497c6e171561813f6a5de6045b84757; Domain=.tiktok.com; Path=/; Secure; Expires=1809938833; tt_csrf_token=mVAY7ZEb-31BTYT0TT2DtZu5AsDSsvBjC9kg; Domain=.tiktok.com; Path=/; Secure; tt_chain_token=\"rLj6efEsYd5gdm8VRZAFaw==\"; Domain=.tiktok.com; Path=/; Secure; Expires=1794386833", "http_headers": {"User-Agent": "Mozilla/5.0 (Windows NT 10.0; Win64; x64) AppleWebKit/537.36 (KHTML, like Gecko) Chrome/143.0.0.0 Safari/537.36", "Accept": "text/html,application/xhtml+xml,application/xml;q=0.9,*/*;q=0.8", "Accept-Language": "en-us,en;q=0.5", "Sec-Fetch-Mode": "navigate", "Referer": "https://www.tiktok.com/@badgirlwyntaaaa/video/7452522186927066410"}, "format": "h264_540p_789650-0 - 576x1024"}, {"ext": "mp4", "vcodec": "h264", "acodec": "aac", "format_id": "h264_540p_789650-1", "tbr": 789, "quality": 1, "preference": -1, "filesize": 5537423, "width": 576, "height": 1024, "url": "https://v19-webapp-prime.us.tiktok.com/video/tos/useast5/tos-useast5-pve-0068-tx/oAYw6gSDnBWkreaFEKjKwAQlEDFZfbKgbRIw7S/?a=1988&bti=ODszNWYuMDE6&&bt=771&ft=4KJMyMzm8Zmo0yzRFa4jVBnodpWrKsd.&mime_type=video_mp4&rc=OjRkZjs4NjhpZGQ6NjtmOEBpM29kZWw5cjdkdzMzZzczNEA1X2JgYTFhXzExMmA2NGNjYSNqbmA2MmRrbGpgLS1kMS9zcw%3D%3D&expire=1779007689&l=202605150847137780C96EA93873025E7D&ply_type=2&policy=2&signature=fe0148ba15038390f58841f79f1ef194&tk=tt_chain_token&btag=e00088000", "protocol": "https", "video_ext": "mp4", "audio_ext": "none", "resolution": "576x1024", "dynamic_range": "SDR", "aspect_ratio": 0.56, "cookies": "ttwid=1%7CGDhFJwSAscwdaQsU5eawTziZsZ-W33086-T8iT4lhh4%7C1778834833%7C915a7b7731c4d546832c9d6cf9c6eda71497c6e171561813f6a5de6045b84757; Domain=.tiktok.com; Path=/; Secure; Expires=1809938833; tt_csrf_token=mVAY7ZEb-31BTYT0TT2DtZu5AsDSsvBjC9kg; Domain=.tiktok.com; Path=/; Secure; tt_chain_token=\"rLj6efEsYd5gdm8VRZAFaw==\"; Domain=.tiktok.com; Path=/; Secure; Expires=1794386833", "http_headers": {"User-Agent": "Mozilla/5.0 (Windows NT 10.0; Win64; x64) AppleWebKit/537.36 (KHTML, like Gecko) Chrome/143.0.0.0 Safari/537.36", "Accept": "text/html,application/xhtml+xml,application/xml;q=0.9,*/*;q=0.8", "Accept-Language": "en-us,en;q=0.5", "Sec-Fetch-Mode": "navigate", "Referer": "https://www.tiktok.com/@badgirlwyntaaaa/video/7452522186927066410"}, "format": "h264_540p_789650-1 - 576x1024"}, {"ext": "mp4", "vcodec": "h265", "acodec": "aac", "format_id": "bytevc1_540p_386297-0", "tbr": 386, "quality": 1, "preference": -1, "filesize": 2708914, "width": 576, "height": 1024, "url": "https://v16-webapp-prime.us.tiktok.com/video/tos/useast5/tos-useast5-pve-0068-tx/ooJ2yVEit4GUZBilptQsyVrCIgKSsEEsABvir/?a=1988&bti=ODszNWYuMDE6&&bt=377&ft=4KJMyMzm8Zmo0yzRFa4jVBnodpWrKsd.&mime_type=video_mp4&rc=Z2czOGU4ZDZpNDU3NDwzNkBpM29kZWw5cjdkdzMzZzczNEAtLWBjLTM1X2IxL2JjLzNiYSNqbmA2MmRrbGpgLS1kMS9zcw%3D%3D&expire=1779007689&l=202605150847137780C96EA93873025E7D&ply_type=2&policy=2&signature=85e7f8de8d57c5739cc4f83be1d1ae33&tk=tt_chain_token&btag=e00088000", "protocol": "https", "video_ext": "mp4", "audio_ext": "none", "resolution": "576x1024", "dynamic_range": "SDR", "aspect_ratio": 0.56, "cookies": "ttwid=1%7CGDhFJwSAscwdaQsU5eawTziZsZ-W33086-T8iT4lhh4%7C1778834833%7C915a7b7731c4d546832c9d6cf9c6eda71497c6e171561813f6a5de6045b84757; Domain=.tiktok.com; Path=/; Secure; Expires=1809938833; tt_csrf_token=mVAY7ZEb-31BTYT0TT2DtZu5AsDSsvBjC9kg; Domain=.tiktok.com; Path=/; Secure; tt_chain_token=\"rLj6efEsYd5gdm8VRZAFaw==\"; Domain=.tiktok.com; Path=/; Secure; Expires=1794386833", "http_headers": {"User-Agent": "Mozilla/5.0 (Windows NT 10.0; Win64; x64) AppleWebKit/537.36 (KHTML, like Gecko) Chrome/143.0.0.0 Safari/537.36", "Accept": "text/html,application/xhtml+xml,application/xml;q=0.9,*/*;q=0.8", "Accept-Language": "en-us,en;q=0.5", "Sec-Fetch-Mode": "navigate", "Referer": "https://www.tiktok.com/@badgirlwyntaaaa/video/7452522186927066410"}, "format": "bytevc1_540p_386297-0 - 576x1024"}, {"ext": "mp4", "vcodec": "h265", "acodec": "aac", "format_id": "bytevc1_540p_386297-1", "tbr": 386, "quality": 1, "preference": -1, "filesize": 2708914, "width": 576, "height": 1024, "url": "https://v19-webapp-prime.us.tiktok.com/video/tos/useast5/tos-useast5-pve-0068-tx/ooJ2yVEit4GUZBilptQsyVrCIgKSsEEsABvir/?a=1988&bti=ODszNWYuMDE6&&bt=377&ft=4KJMyMzm8Zmo0yzRFa4jVBnodpWrKsd.&mime_type=video_mp4&rc=Z2czOGU4ZDZpNDU3NDwzNkBpM29kZWw5cjdkdzMzZzczNEAtLWBjLTM1X2IxL2JjLzNiYSNqbmA2MmRrbGpgLS1kMS9zcw%3D%3D&expire=1779007689&l=202605150847137780C96EA93873025E7D&ply_type=2&policy=2&signature=85e7f8de8d57c5739cc4f83be1d1ae33&tk=tt_chain_token&btag=e00088000", "protocol": "https", "video_ext": "mp4", "audio_ext": "none", "resolution": "576x1024", "dynamic_range": "SDR", "aspect_ratio": 0.56, "cookies": "ttwid=1%7CGDhFJwSAscwdaQsU5eawTziZsZ-W33086-T8iT4lhh4%7C1778834833%7C915a7b7731c4d546832c9d6cf9c6eda71497c6e171561813f6a5de6045b84757; Domain=.tiktok.com; Path=/; Secure; Expires=1809938833; tt_csrf_token=mVAY7ZEb-31BTYT0TT2DtZu5AsDSsvBjC9kg; Domain=.tiktok.com; Path=/; Secure; tt_chain_token=\"rLj6efEsYd5gdm8VRZAFaw==\"; Domain=.tiktok.com; Path=/; Secure; Expires=1794386833", "http_headers": {"User-Agent": "Mozilla/5.0 (Windows NT 10.0; Win64; x64) AppleWebKit/537.36 (KHTML, like Gecko) Chrome/143.0.0.0 Safari/537.36", "Accept": "text/html,application/xhtml+xml,application/xml;q=0.9,*/*;q=0.8", "Accept-Language": "en-us,en;q=0.5", "Sec-Fetch-Mode": "navigate", "Referer": "https://www.tiktok.com/@badgirlwyntaaaa/video/7452522186927066410"}, "format": "bytevc1_540p_386297-1 - 576x1024"}, {"ext": "mp4", "vcodec": "h265", "acodec": "aac", "format_id": "bytevc1_720p_459177-0", "tbr": 459, "quality": 2, "preference": -1, "filesize": 3219983, "width": 720, "height": 1280, "url": "https://v16-webapp-prime.us.tiktok.com/video/tos/useast5/tos-useast5-ve-0068c001-tx/oUr4rtZSEsVshiivUsSQ2ytBsgiEEQInDEBAy/?a=1988&bti=ODszNWYuMDE6&&bt=448&ft=4KJMyMzm8Zmo0yzRFa4jVBnodpWrKsd.&mime_type=video_mp4&rc=PGZmO2c5PDo1ZDY0O2g3NEBpM29kZWw5cjdkdzMzZzczNEBiLTIyLWMxNWAxXjUuYjU1YSNqbmA2MmRrbGpgLS1kMS9zcw%3D%3D&expire=1779007689&l=202605150847137780C96EA93873025E7D&ply_type=2&policy=2&signature=ca6b28960303749ddfae7683cd9f2ead&tk=tt_chain_token&btag=e00088000", "protocol": "https", "video_ext": "mp4", "audio_ext": "none", "resolution": "720x1280", "dynamic_range": "SDR", "aspect_ratio": 0.56, "cookies": "ttwid=1%7CGDhFJwSAscwdaQsU5eawTziZsZ-W33086-T8iT4lhh4%7C1778834833%7C915a7b7731c4d546832c9d6cf9c6eda71497c6e171561813f6a5de6045b84757; Domain=.tiktok.com; Path=/; Secure; Expires=1809938833; tt_csrf_token=mVAY7ZEb-31BTYT0TT2DtZu5AsDSsvBjC9kg; Domain=.tiktok.com; Path=/; Secure; tt_chain_token=\"rLj6efEsYd5gdm8VRZAFaw==\"; Domain=.tiktok.com; Path=/; Secure; Expires=1794386833", "http_headers": {"User-Agent": "Mozilla/5.0 (Windows NT 10.0; Win64; x64) AppleWebKit/537.36 (KHTML, like Gecko) Chrome/143.0.0.0 Safari/537.36", "Accept": "text/html,application/xhtml+xml,application/xml;q=0.9,*/*;q=0.8", "Accept-Language": "en-us,en;q=0.5", "Sec-Fetch-Mode": "navigate", "Referer": "https://www.tiktok.com/@badgirlwyntaaaa/video/7452522186927066410"}, "format": "bytevc1_720p_459177-0 - 720x1280"}, {"ext": "mp4", "vcodec": "h265", "acodec": "aac", "format_id": "bytevc1_720p_459177-1", "tbr": 459, "quality": 2, "preference": -1, "filesize": 3219983, "width": 720, "height": 1280, "url": "https://v19-webapp-prime.us.tiktok.com/video/tos/useast5/tos-useast5-ve-0068c001-tx/oUr4rtZSEsVshiivUsSQ2ytBsgiEEQInDEBAy/?a=1988&bti=ODszNWYuMDE6&&bt=448&ft=4KJMyMzm8Zmo0yzRFa4jVBnodpWrKsd.&mime_type=video_mp4&rc=PGZmO2c5PDo1ZDY0O2g3NEBpM29kZWw5cjdkdzMzZzczNEBiLTIyLWMxNWAxXjUuYjU1YSNqbmA2MmRrbGpgLS1kMS9zcw%3D%3D&expire=1779007689&l=202605150847137780C96EA93873025E7D&ply_type=2&policy=2&signature=ca6b28960303749ddfae7683cd9f2ead&tk=tt_chain_token&btag=e00088000", "protocol": "https", "video_ext": "mp4", "audio_ext": "none", "resolution": "720x1280", "dynamic_range": "SDR", "aspect_ratio": 0.56, "cookies": "ttwid=1%7CGDhFJwSAscwdaQsU5eawTziZsZ-W33086-T8iT4lhh4%7C1778834833%7C915a7b7731c4d546832c9d6cf9c6eda71497c6e171561813f6a5de6045b84757; Domain=.tiktok.com; Path=/; Secure; Expires=1809938833; tt_csrf_token=mVAY7ZEb-31BTYT0TT2DtZu5AsDSsvBjC9kg; Domain=.tiktok.com; Path=/; Secure; tt_chain_token=\"rLj6efEsYd5gdm8VRZAFaw==\"; Domain=.tiktok.com; Path=/; Secure; Expires=1794386833", "http_headers": {"User-Agent": "Mozilla/5.0 (Windows NT 10.0; Win64; x64) AppleWebKit/537.36 (KHTML, like Gecko) Chrome/143.0.0.0 Safari/537.36", "Accept": "text/html,application/xhtml+xml,application/xml;q=0.9,*/*;q=0.8", "Accept-Language": "en-us,en;q=0.5", "Sec-Fetch-Mode": "navigate", "Referer": "https://www.tiktok.com/@badgirlwyntaaaa/video/7452522186927066410"}, "format": "bytevc1_720p_459177-1 - 720x1280"}, {"ext": "mp4", "vcodec": "h265", "acodec": "aac", "format_id": "bytevc1_1080p_699845-0", "tbr": 699, "quality": 3, "preference": -1, "filesize": 4907668, "width": 1080, "height": 1920, "url": "https://v16-webapp-prime.us.tiktok.com/video/tos/useast5/tos-useast5-ve-0068c004-tx/ogW2yhEit46UZBirktQsyV6EIgPSsEEsABvit/?a=1988&bti=ODszNWYuMDE6&&bt=683&ft=4KJMyMzm8Zmo0yzRFa4jVBnodpWrKsd.&mime_type=video_mp4&rc=ZDk3ZDY0ZDk7PDw4Mzk8aUBpM29kZWw5cjdkdzMzZzczNEAyMGEwYi5fXjQxLWI0Y14zYSNqbmA2MmRrbGpgLS1kMS9zcw%3D%3D&expire=1779007689&l=202605150847137780C96EA93873025E7D&ply_type=2&policy=2&signature=7b22d7af60a00ec7ca199011fd4a11fd&tk=tt_chain_token&btag=e00088000", "protocol": "https", "video_ext": "mp4", "audio_ext": "none", "resolution": "1080x1920", "dynamic_range": "SDR", "aspect_ratio": 0.56, "cookies": "ttwid=1%7CGDhFJwSAscwdaQsU5eawTziZsZ-W33086-T8iT4lhh4%7C1778834833%7C915a7b7731c4d546832c9d6cf9c6eda71497c6e171561813f6a5de6045b84757; Domain=.tiktok.com; Path=/; Secure; Expires=1809938833; tt_csrf_token=mVAY7ZEb-31BTYT0TT2DtZu5AsDSsvBjC9kg; Domain=.tiktok.com; Path=/; Secure; tt_chain_token=\"rLj6efEsYd5gdm8VRZAFaw==\"; Domain=.tiktok.com; Path=/; Secure; Expires=1794386833", "http_headers": {"User-Agent": "Mozilla/5.0 (Windows NT 10.0; Win64; x64) AppleWebKit/537.36 (KHTML, like Gecko) Chrome/143.0.0.0 Safari/537.36", "Accept": "text/html,application/xhtml+xml,application/xml;q=0.9,*/*;q=0.8", "Accept-Language": "en-us,en;q=0.5", "Sec-Fetch-Mode": "navigate", "Referer": "https://www.tiktok.com/@badgirlwyntaaaa/video/7452522186927066410"}, "format": "bytevc1_1080p_699845-0 - 1080x1920"}, {"ext": "mp4", "vcodec": "h265", "acodec": "aac", "format_id": "bytevc1_1080p_699845-1", "tbr": 699, "quality": 3, "preference": -1, "filesize": 4907668, "width": 1080, "height": 1920, "url": "https://v19-webapp-prime.us.tiktok.com/video/tos/useast5/tos-useast5-ve-0068c004-tx/ogW2yhEit46UZBirktQsyV6EIgPSsEEsABvit/?a=1988&bti=ODszNWYuMDE6&&bt=683&ft=4KJMyMzm8Zmo0yzRFa4jVBnodpWrKsd.&mime_type=video_mp4&rc=ZDk3ZDY0ZDk7PDw4Mzk8aUBpM29kZWw5cjdkdzMzZzczNEAyMGEwYi5fXjQxLWI0Y14zYSNqbmA2MmRrbGpgLS1kMS9zcw%3D%3D&expire=1779007689&l=202605150847137780C96EA93873025E7D&ply_type=2&policy=2&signature=7b22d7af60a00ec7ca199011fd4a11fd&tk=tt_chain_token&btag=e00088000", "protocol": "https", "video_ext": "mp4", "audio_ext": "none", "resolution": "1080x1920", "dynamic_range": "SDR", "aspect_ratio": 0.56, "cookies": "ttwid=1%7CGDhFJwSAscwdaQsU5eawTziZsZ-W33086-T8iT4lhh4%7C1778834833%7C915a7b7731c4d546832c9d6cf9c6eda71497c6e171561813f6a5de6045b84757; Domain=.tiktok.com; Path=/; Secure; Expires=1809938833; tt_csrf_token=mVAY7ZEb-31BTYT0TT2DtZu5AsDSsvBjC9kg; Domain=.tiktok.com; Path=/; Secure; tt_chain_token=\"rLj6efEsYd5gdm8VRZAFaw==\"; Domain=.tiktok.com; Path=/; Secure; Expires=1794386833", "http_headers": {"User-Agent": "Mozilla/5.0 (Windows NT 10.0; Win64; x64) AppleWebKit/537.36 (KHTML, like Gecko) Chrome/143.0.0.0 Safari/537.36", "Accept": "text/html,application/xhtml+xml,application/xml;q=0.9,*/*;q=0.8", "Accept-Language": "en-us,en;q=0.5", "Sec-Fetch-Mode": "navigate", "Referer": "https://www.tiktok.com/@badgirlwyntaaaa/video/7452522186927066410"}, "format": "bytevc1_1080p_699845-1 - 1080x1920"}], "subtitles": {}, "http_headers": {"User-Agent": "Mozilla/5.0 (Windows NT 10.0; Win64; x64) AppleWebKit/537.36 (KHTML, like Gecko) Chrome/143.0.0.0 Safari/537.36", "Accept": "text/html,application/xhtml+xml,application/xml;q=0.9,*/*;q=0.8", "Accept-Language": "en-us,en;q=0.5", "Sec-Fetch-Mode": "navigate", "Referer": "https://www.tiktok.com/@badgirlwyntaaaa/video/7452522186927066410"}, "channel": "Ms. Wynterrrrrr🧚🏾‍♀️", "channel_id": "MS4wLjABAAAAn0IrZr69xs4OA2hbGsqopZkPLdn-KgtOtmXtnNo04o06glN2QmvuoRA61cRI6KZ4", "uploader": "badgirlwyntaaaa", "uploader_id": "6765891332852007942", "channel_url": "https://www.tiktok.com/@MS4wLjABAAAAn0IrZr69xs4OA2hbGsqopZkPLdn-KgtOtmXtnNo04o06glN2QmvuoRA61cRI6KZ4", "uploader_url": "https://www.tiktok.com/@badgirlwyntaaaa", "track": "Peggy", "album": "Peggy", "artists": ["Ceechynaa"], "duration": 56, "title": "wasn’t the reaction I was expecting 😭😭😭😭 #fypシ゚viral  @Moni Q ", "description": "wasn’t the reaction I was expecting 😭😭😭😭 #fypシ゚viral  @Moni Q ", "timestamp": 1735175541, "view_count": 11400000, "like_count": 2400000, "repost_count": 89400, "comment_count": 7634, "save_count": 150337, "thumbnails": [{"id": "dynamicCover", "url": "https://p19-common-sign.tiktokcdn-us.com/tos-useast5-p-0068-tx/ooDEFWauQlkESAbBrZeDfDYRwSAFCEKgzUjnQb~tplv-tiktokx-origin.image?dr=9636&x-expires=1779004800&x-signature=WDqHN55j3efCv0dPZic1g5SYTM8%3D&t=4d5b0474&ps=13740610&shp=81f88b70&shcp=43f4a2f9&idc=useast5", "preference": -2}, {"id": "cover", "url": "https://p19-common-sign.tiktokcdn-us.com/tos-useast5-p-0068-tx/oYIEZFnlKBKrDFDhQfAh6SCgEfWbYbkSaDwARu~tplv-tiktokx-origin.image?dr=9636&x-expires=1779004800&x-signature=mMlwpaN0XbhbEBBjV38oP1ED2vE%3D&t=4d5b0474&ps=13740610&shp=81f88b70&shcp=43f4a2f9&idc=useast5", "preference": -1}, {"id": "originCover", "url": "https://p16-common-sign.tiktokcdn-us.com/tos-useast5-p-0068-tx/o8uKyDbdQASSlrBEkDWE3aw2fQzRgRFFnZBbYf~tplv-tiktokx-origin.image?dr=9636&x-expires=1779004800&x-signature=u4ADs0gAV0yyMhZxTZtJw4h6zgE%3D&t=4d5b0474&ps=13740610&shp=81f88b70&shcp=43f4a2f9&idc=useast5", "preference": -1}], "webpage_url": "https://www.tiktok.com/@badgirlwyntaaaa/video/7452522186927066410", "webpage_url_basename": "7452522186927066410", "webpage_url_domain": "tiktok.com", "extractor": "TikTok", "extractor_key": "TikTok", "thumbnail": "https://p16-common-sign.tiktokcdn-us.com/tos-useast5-p-0068-tx/o8uKyDbdQASSlrBEkDWE3aw2fQzRgRFFnZBbYf~tplv-tiktokx-origin.image?dr=9636&x-expires=1779004800&x-signature=u4ADs0gAV0yyMhZxTZtJw4h6zgE%3D&t=4d5b0474&ps=13740610&shp=81f88b70&shcp=43f4a2f9&idc=useast5", "display_id": "7452522186927066410", "fulltitle": "wasn’t the reaction I was expecting 😭😭😭😭 #fypシ゚viral  @Moni Q ", "duration_string": "56", "upload_date": "20241226", "artist": "Ceechynaa", "epoch": 1778834833, "ext": "mp4", "vcodec": "h265", "acodec": "aac", "format_id": "bytevc1_1080p_699845-1", "tbr": 699, "quality": 3, "preference": -1, "filesize": 4907668, "width": 1080, "height": 1920, "url": "https://v19-webapp-prime.us.tiktok.com/video/tos/useast5/tos-useast5-ve-0068c004-tx/ogW2yhEit46UZBirktQsyV6EIgPSsEEsABvit/?a=1988&bti=ODszNWYuMDE6&&bt=683&ft=4KJMyMzm8Zmo0yzRFa4jVBnodpWrKsd.&mime_type=video_mp4&rc=ZDk3ZDY0ZDk7PDw4Mzk8aUBpM29kZWw5cjdkdzMzZzczNEAyMGEwYi5fXjQxLWI0Y14zYSNqbmA2MmRrbGpgLS1kMS9zcw%3D%3D&expire=1779007689&l=202605150847137780C96EA93873025E7D&ply_type=2&policy=2&signature=7b22d7af60a00ec7ca199011fd4a11fd&tk=tt_chain_token&btag=e00088000", "protocol": "https", "video_ext": "mp4", "audio_ext": "none", "resolution": "1080x1920", "dynamic_range": "SDR", "aspect_ratio": 0.56, "cookies": "ttwid=1%7CGDhFJwSAscwdaQsU5eawTziZsZ-W33086-T8iT4lhh4%7C1778834833%7C915a7b7731c4d546832c9d6cf9c6eda71497c6e171561813f6a5de6045b84757; Domain=.tiktok.com; Path=/; Secure; Expires=1809938833; tt_csrf_token=mVAY7ZEb-31BTYT0TT2DtZu5AsDSsvBjC9kg; Domain=.tiktok.com; Path=/; Secure; tt_chain_token=\"rLj6efEsYd5gdm8VRZAFaw==\"; Domain=.tiktok.com; Path=/; Secure; Expires=1794386833", "format": "bytevc1_1080p_699845-1 - 1080x1920", "_type": "video", "_version": {"version": "2026.03.17", "release_git_head": "04d6974f502bbdfaed72c624344f262e30ad9708", "repository": "yt-dlp/yt-dlp"}}