{"id": "7176477300643548462", "formats": [{"ext": "mp4", "vcodec": "h264", "acodec": "aac", "format_id": "download", "url": "https://v16-webapp-prime.us.tiktok.com/video/tos/useast5/tos-useast5-ve-0068c004-tx/o4AQ1ibUnIGKi6ElcC076Z4i2QGEBAZv4hg6l/?a=1988&bti=ODszNWYuMDE6&&bt=967&ft=4KJMyMzm8Zmo0Em8da4jVSE.dpWrKsd.&mime_type=video_mp4&rc=ZTo0aDllO2Q4Nzg1PDxlPEBpM242Z3U5cnJzeDMzZzgzNEBjNF41MS5jNTExMy5hYi1iYSMyaWZxMmRrbWRgLS1kLy9zcw%3D%3D&expire=1781513757&l=20260613085539FAC5EBA1F64ACB50D095&ply_type=2&policy=2&signature=607134d27af2cb08ae0c8d123ca670f6&tk=tt_chain_token&btag=e000b8000", "format_note": "watermarked", "preference": -2, "protocol": "https", "video_ext": "mp4", "audio_ext": "none", "dynamic_range": "SDR", "cookies": "ttwid=1%7CnqztF2Gq5tq-TxmaFuRVAaBLjMweFx-ZhCu7kLO7fO8%7C1781340939%7C1dc7729a592e493b6e0ad01686bb0af167f06c0b8a9fcd28d7a1f1b080752931; Domain=.tiktok.com; Path=/; Secure; Expires=1812444939; tt_csrf_token=lx4V3f9T-WanNHNBdIv9Mhp97qcwqnrc7zp8; Domain=.tiktok.com; Path=/; Secure; tt_chain_token=\"LoVkybpry430FD70YClwjQ==\"; Domain=.tiktok.com; Path=/; Secure; Expires=1796892939", "http_headers": {"User-Agent": "Mozilla/5.0 (Windows NT 10.0; Win64; x64) AppleWebKit/537.36 (KHTML, like Gecko) Chrome/148.0.0.0 Safari/537.36", "Accept": "text/html,application/xhtml+xml,application/xml;q=0.9,*/*;q=0.8", "Accept-Language": "en-us,en;q=0.5", "Sec-Fetch-Mode": "navigate", "Referer": "https://www.tiktok.com/@itzgalan/video/7176477300643548462"}, "format": "download - unknown (watermarked)"}, {"ext": "mp4", "vcodec": "h264", "acodec": "aac", "format_id": "h264_540p_420271-0", "tbr": 420, "quality": 1, "preference": -1, "filesize": 921024, "width": 576, "height": 1024, "url": "https://v16-webapp-prime.us.tiktok.com/video/tos/useast5/tos-useast5-pve-0068-tx/osCO6G77EIlK0vQK64ZiAhBUO3i2gD6D4cnAc/?a=1988&bti=ODszNWYuMDE6&&bt=410&ft=4KJMyMzm8Zmo0Em8da4jVSE.dpWrKsd.&mime_type=video_mp4&rc=NTxmPGhpOTQ5Zzk2NTw5Z0BpM242Z3U5cnJzeDMzZzgzNEA2MDJhYS5eNjQxYTE1LmM0YSMyaWZxMmRrbWRgLS1kLy9zcw%3D%3D&expire=1781513757&l=20260613085539FAC5EBA1F64ACB50D095&ply_type=2&policy=2&signature=c4d9f94a53d8faf3895dbe9a005c6ab5&tk=tt_chain_token&btag=e000b8000", "protocol": "https", "video_ext": "mp4", "audio_ext": "none", "resolution": "576x1024", "dynamic_range": "SDR", "aspect_ratio": 0.56, "cookies": "ttwid=1%7CnqztF2Gq5tq-TxmaFuRVAaBLjMweFx-ZhCu7kLO7fO8%7C1781340939%7C1dc7729a592e493b6e0ad01686bb0af167f06c0b8a9fcd28d7a1f1b080752931; Domain=.tiktok.com; Path=/; Secure; Expires=1812444939; tt_csrf_token=lx4V3f9T-WanNHNBdIv9Mhp97qcwqnrc7zp8; Domain=.tiktok.com; Path=/; Secure; tt_chain_token=\"LoVkybpry430FD70YClwjQ==\"; Domain=.tiktok.com; Path=/; Secure; Expires=1796892939", "http_headers": {"User-Agent": "Mozilla/5.0 (Windows NT 10.0; Win64; x64) AppleWebKit/537.36 (KHTML, like Gecko) Chrome/148.0.0.0 Safari/537.36", "Accept": "text/html,application/xhtml+xml,application/xml;q=0.9,*/*;q=0.8", "Accept-Language": "en-us,en;q=0.5", "Sec-Fetch-Mode": "navigate", "Referer": "https://www.tiktok.com/@itzgalan/video/7176477300643548462"}, "format": "h264_540p_420271-0 - 576x1024"}, {"ext": "mp4", "vcodec": "h264", "acodec": "aac", "format_id": "h264_540p_420271-1", "tbr": 420, "quality": 1, "preference": -1, "filesize": 921024, "width": 576, "height": 1024, "url": "https://v19-webapp-prime.us.tiktok.com/video/tos/useast5/tos-useast5-pve-0068-tx/osCO6G77EIlK0vQK64ZiAhBUO3i2gD6D4cnAc/?a=1988&bti=ODszNWYuMDE6&&bt=410&ft=4KJMyMzm8Zmo0Em8da4jVSE.dpWrKsd.&mime_type=video_mp4&rc=NTxmPGhpOTQ5Zzk2NTw5Z0BpM242Z3U5cnJzeDMzZzgzNEA2MDJhYS5eNjQxYTE1LmM0YSMyaWZxMmRrbWRgLS1kLy9zcw%3D%3D&expire=1781513757&l=20260613085539FAC5EBA1F64ACB50D095&ply_type=2&policy=2&signature=c4d9f94a53d8faf3895dbe9a005c6ab5&tk=tt_chain_token&btag=e000b8000", "protocol": "https", "video_ext": "mp4", "audio_ext": "none", "resolution": "576x1024", "dynamic_range": "SDR", "aspect_ratio": 0.56, "cookies": "ttwid=1%7CnqztF2Gq5tq-TxmaFuRVAaBLjMweFx-ZhCu7kLO7fO8%7C1781340939%7C1dc7729a592e493b6e0ad01686bb0af167f06c0b8a9fcd28d7a1f1b080752931; Domain=.tiktok.com; Path=/; Secure; Expires=1812444939; tt_csrf_token=lx4V3f9T-WanNHNBdIv9Mhp97qcwqnrc7zp8; Domain=.tiktok.com; Path=/; Secure; tt_chain_token=\"LoVkybpry430FD70YClwjQ==\"; Domain=.tiktok.com; Path=/; Secure; Expires=1796892939", "http_headers": {"User-Agent": "Mozilla/5.0 (Windows NT 10.0; Win64; x64) AppleWebKit/537.36 (KHTML, like Gecko) Chrome/148.0.0.0 Safari/537.36", "Accept": "text/html,application/xhtml+xml,application/xml;q=0.9,*/*;q=0.8", "Accept-Language": "en-us,en;q=0.5", "Sec-Fetch-Mode": "navigate", "Referer": "https://www.tiktok.com/@itzgalan/video/7176477300643548462"}, "format": "h264_540p_420271-1 - 576x1024"}, {"ext": "mp4", "vcodec": "h264", "acodec": "aac", "format_id": "h264_540p_944368-0", "tbr": 944, "quality": 1, "preference": -1, "filesize": 2069583, "width": 576, "height": 1024, "url": "https://v16-webapp-prime.us.tiktok.com/video/tos/useast5/tos-useast5-ve-0068c002-tx/owYzQSU1iDAOnsDpeZF3DVngWC1goBGoIhf2hE/?a=1988&bti=ODszNWYuMDE6&&bt=922&ft=4KJMyMzm8Zmo0Em8da4jVSE.dpWrKsd.&mime_type=video_mp4&rc=OjY6ZGRkZzk0M2dmZ2RlNEBpM242Z3U5cnJzeDMzZzgzNEAvMTYvLzUtXmMxNF41MDFhYSMyaWZxMmRrbWRgLS1kLy9zcw%3D%3D&expire=1781513757&l=20260613085539FAC5EBA1F64ACB50D095&ply_type=2&policy=2&signature=4579c89f065ffeda9ff471305b45af91&tk=tt_chain_token&btag=e000b8000", "protocol": "https", "video_ext": "mp4", "audio_ext": "none", "resolution": "576x1024", "dynamic_range": "SDR", "aspect_ratio": 0.56, "cookies": "ttwid=1%7CnqztF2Gq5tq-TxmaFuRVAaBLjMweFx-ZhCu7kLO7fO8%7C1781340939%7C1dc7729a592e493b6e0ad01686bb0af167f06c0b8a9fcd28d7a1f1b080752931; Domain=.tiktok.com; Path=/; Secure; Expires=1812444939; tt_csrf_token=lx4V3f9T-WanNHNBdIv9Mhp97qcwqnrc7zp8; Domain=.tiktok.com; Path=/; Secure; tt_chain_token=\"LoVkybpry430FD70YClwjQ==\"; Domain=.tiktok.com; Path=/; Secure; Expires=1796892939", "http_headers": {"User-Agent": "Mozilla/5.0 (Windows NT 10.0; Win64; x64) AppleWebKit/537.36 (KHTML, like Gecko) Chrome/148.0.0.0 Safari/537.36", "Accept": "text/html,application/xhtml+xml,application/xml;q=0.9,*/*;q=0.8", "Accept-Language": "en-us,en;q=0.5", "Sec-Fetch-Mode": "navigate", "Referer": "https://www.tiktok.com/@itzgalan/video/7176477300643548462"}, "format": "h264_540p_944368-0 - 576x1024"}, {"ext": "mp4", "vcodec": "h264", "acodec": "aac", "format_id": "h264_540p_944368-1", "tbr": 944, "quality": 1, "preference": -1, "filesize": 2069583, "width": 576, "height": 1024, "url": "https://v19-webapp-prime.us.tiktok.com/video/tos/useast5/tos-useast5-ve-0068c002-tx/owYzQSU1iDAOnsDpeZF3DVngWC1goBGoIhf2hE/?a=1988&bti=ODszNWYuMDE6&&bt=922&ft=4KJMyMzm8Zmo0Em8da4jVSE.dpWrKsd.&mime_type=video_mp4&rc=OjY6ZGRkZzk0M2dmZ2RlNEBpM242Z3U5cnJzeDMzZzgzNEAvMTYvLzUtXmMxNF41MDFhYSMyaWZxMmRrbWRgLS1kLy9zcw%3D%3D&expire=1781513757&l=20260613085539FAC5EBA1F64ACB50D095&ply_type=2&policy=2&signature=4579c89f065ffeda9ff471305b45af91&tk=tt_chain_token&btag=e000b8000", "protocol": "https", "video_ext": "mp4", "audio_ext": "none", "resolution": "576x1024", "dynamic_range": "SDR", "aspect_ratio": 0.56, "cookies": "ttwid=1%7CnqztF2Gq5tq-TxmaFuRVAaBLjMweFx-ZhCu7kLO7fO8%7C1781340939%7C1dc7729a592e493b6e0ad01686bb0af167f06c0b8a9fcd28d7a1f1b080752931; Domain=.tiktok.com; Path=/; Secure; Expires=1812444939; tt_csrf_token=lx4V3f9T-WanNHNBdIv9Mhp97qcwqnrc7zp8; Domain=.tiktok.com; Path=/; Secure; tt_chain_token=\"LoVkybpry430FD70YClwjQ==\"; Domain=.tiktok.com; Path=/; Secure; Expires=1796892939", "http_headers": {"User-Agent": "Mozilla/5.0 (Windows NT 10.0; Win64; x64) AppleWebKit/537.36 (KHTML, like Gecko) Chrome/148.0.0.0 Safari/537.36", "Accept": "text/html,application/xhtml+xml,application/xml;q=0.9,*/*;q=0.8", "Accept-Language": "en-us,en;q=0.5", "Sec-Fetch-Mode": "navigate", "Referer": "https://www.tiktok.com/@itzgalan/video/7176477300643548462"}, "format": "h264_540p_944368-1 - 576x1024"}], "subtitles": {}, "http_headers": {"User-Agent": "Mozilla/5.0 (Windows NT 10.0; Win64; x64) AppleWebKit/537.36 (KHTML, like Gecko) Chrome/148.0.0.0 Safari/537.36", "Accept": "text/html,application/xhtml+xml,application/xml;q=0.9,*/*;q=0.8", "Accept-Language": "en-us,en;q=0.5", "Sec-Fetch-Mode": "navigate", "Referer": "https://www.tiktok.com/@itzgalan/video/7176477300643548462"}, "channel": "Galan🇩🇴", "channel_id": "MS4wLjABAAAAMJb4Hk0eiNYsVwlw9zVoV-aZICfAXCx4FU-gzuBPjzCM5MaGZMaa9kGr1jV3yNPf", "uploader": "itzgalan", "uploader_id": "6764880761108808709", "channel_url": "https://www.tiktok.com/@MS4wLjABAAAAMJb4Hk0eiNYsVwlw9zVoV-aZICfAXCx4FU-gzuBPjzCM5MaGZMaa9kGr1jV3yNPf", "uploader_url": "https://www.tiktok.com/@itzgalan", "track": "Goodbyeeee", "artists": ["rreapwock"], "duration": 17, "title": "Bro I’ve seen this video like 20 times already😂 #fyp #viral #xyzbca #...", "description": "Bro I’ve seen this video like 20 times already😂 #fyp #viral #xyzbca #contentcreator #ronaldo #worldcup2022 ", "timestamp": 1670903846, "view_count": 25300000, "like_count": 3500000, "repost_count": 295000, "comment_count": 27100, "save_count": 247079, "thumbnails": [{"id": "dynamicCover", "url": "https://p19-common-sign.tiktokcdn-us.com/tos-useast5-p-0068-tx/ooO6l650cBKgMAT7bQhhvqIBiA6iZIn4U4GK2~tplv-tiktokx-origin.image?dr=9636&x-expires=1781510400&x-signature=jvxLTOMisufs0kVG6lCYc%2FYkMEQ%3D&t=4d5b0474&ps=13740610&shp=81f88b70&shcp=43f4a2f9&idc=useast5", "preference": -2}, {"id": "cover", "url": "https://p19-common-sign.tiktokcdn-us.com/tos-useast5-p-0068-tx/ogsOhA1SZSBLhEQneoFfDBgaonOdzUI1VMD3Ci~tplv-tiktokx-origin.image?dr=9636&x-expires=1781510400&x-signature=V0fof3%2FKlmxok5iAvK1GsanLTtQ%3D&t=4d5b0474&ps=13740610&shp=81f88b70&shcp=43f4a2f9&idc=useast5", "preference": -1}, {"id": "originCover", "url": "https://p19-common-sign.tiktokcdn-us.com/tos-useast5-p-0068-tx/owPv2I4g6I4zEAUq7yycKAtiB6QGZAnOi06lh~tplv-tiktokx-origin.image?dr=9636&x-expires=1781510400&x-signature=AKyQQo2ciYaDUoO5JUige0jM3Pw%3D&t=4d5b0474&ps=13740610&shp=81f88b70&shcp=43f4a2f9&idc=useast5", "preference": -1}], "webpage_url": "https://www.tiktok.com/@itzgalan/video/7176477300643548462", "webpage_url_basename": "7176477300643548462", "webpage_url_domain": "tiktok.com", "extractor": "TikTok", "extractor_key": "TikTok", "thumbnail": "https://p19-common-sign.tiktokcdn-us.com/tos-useast5-p-0068-tx/owPv2I4g6I4zEAUq7yycKAtiB6QGZAnOi06lh~tplv-tiktokx-origin.image?dr=9636&x-expires=1781510400&x-signature=AKyQQo2ciYaDUoO5JUige0jM3Pw%3D&t=4d5b0474&ps=13740610&shp=81f88b70&shcp=43f4a2f9&idc=useast5", "display_id": "7176477300643548462", "fulltitle": "Bro I’ve seen this video like 20 times already😂 #fyp #viral #xyzbca #...", "duration_string": "17", "upload_date": "20221213", "artist": "rreapwock", "epoch": 1781340940, "ext": "mp4", "vcodec": "h264", "acodec": "aac", "format_id": "h264_540p_944368-1", "tbr": 944, "quality": 1, "preference": -1, "filesize": 2069583, "width": 576, "height": 1024, "url": "https://v19-webapp-prime.us.tiktok.com/video/tos/useast5/tos-useast5-ve-0068c002-tx/owYzQSU1iDAOnsDpeZF3DVngWC1goBGoIhf2hE/?a=1988&bti=ODszNWYuMDE6&&bt=922&ft=4KJMyMzm8Zmo0Em8da4jVSE.dpWrKsd.&mime_type=video_mp4&rc=OjY6ZGRkZzk0M2dmZ2RlNEBpM242Z3U5cnJzeDMzZzgzNEAvMTYvLzUtXmMxNF41MDFhYSMyaWZxMmRrbWRgLS1kLy9zcw%3D%3D&expire=1781513757&l=20260613085539FAC5EBA1F64ACB50D095&ply_type=2&policy=2&signature=4579c89f065ffeda9ff471305b45af91&tk=tt_chain_token&btag=e000b8000", "protocol": "https", "video_ext": "mp4", "audio_ext": "none", "resolution": "576x1024", "dynamic_range": "SDR", "aspect_ratio": 0.56, "cookies": "ttwid=1%7CnqztF2Gq5tq-TxmaFuRVAaBLjMweFx-ZhCu7kLO7fO8%7C1781340939%7C1dc7729a592e493b6e0ad01686bb0af167f06c0b8a9fcd28d7a1f1b080752931; Domain=.tiktok.com; Path=/; Secure; Expires=1812444939; tt_csrf_token=lx4V3f9T-WanNHNBdIv9Mhp97qcwqnrc7zp8; Domain=.tiktok.com; Path=/; Secure; tt_chain_token=\"LoVkybpry430FD70YClwjQ==\"; Domain=.tiktok.com; Path=/; Secure; Expires=1796892939", "format": "h264_540p_944368-1 - 576x1024", "_type": "video", "_version": {"version": "2026.06.09", "release_git_head": "821bef0f00178916d60dbc86bc0bcb8cc3bae8d5", "repository": "yt-dlp/yt-dlp"}}