{"id": "7646862763834281238", "formats": [{"ext": "mp4", "vcodec": "h264", "acodec": "aac", "format_id": "download", "url": "https://v16-webapp-prime.us.tiktok.com/video/tos/no1a/tos-no1a-ve-0068-no/oI4j4PQAZP4HKfIUIemtHcAgM8AtXLAMvDfUjR/?a=1988&bti=ODszNWYuMDE6&&bt=1009&eid=5376&ft=aEeq8qT0mIoPD12gdEYI3wU3IBAbMeF~O5&mime_type=video_mp4&rc=ZDloOTYzZzU5Nzs0Mzw8ZEBpM21za3k5cm9rOzMzbzczNUA2LzYzNjMvXl8xNS4uM2ExYSM0a3AwMmRrbWNhLS1kMTFzcw%3D%3D&expire=1780995292&l=202606070854197D3070279F844563BF08&ply_type=2&policy=2&signature=f1717b2ca61868e66cad77a6f221052f&tk=tt_chain_token&btag=e00088000", "format_note": "watermarked", "preference": -2, "protocol": "https", "video_ext": "mp4", "audio_ext": "none", "dynamic_range": "SDR", "cookies": "ttwid=1%7CJjuPNQnL9us0mldMg1qOGv3JzVsT-DjrHrHAnFblR78%7C1780822459%7C28bf628f30aa8ab8f6602fa0fde3e80c30f7ff8b5a938c9d2b2cdcb25f3a432c; Domain=.tiktok.com; Path=/; Secure; Expires=1811926459; tt_csrf_token=dBth9Rgj-luKI95LCZNJRQ-L1VI5_tl_MLZ8; Domain=.tiktok.com; Path=/; Secure; tt_chain_token=\"MTliXtHu0wXJFnObCfPdhg==\"; Domain=.tiktok.com; Path=/; Secure; Expires=1796374460", "http_headers": {"User-Agent": "Mozilla/5.0 (Windows NT 10.0; Win64; x64) AppleWebKit/537.36 (KHTML, like Gecko) Chrome/141.0.0.0 Safari/537.36", "Accept": "text/html,application/xhtml+xml,application/xml;q=0.9,*/*;q=0.8", "Accept-Language": "en-us,en;q=0.5", "Sec-Fetch-Mode": "navigate", "Referer": "https://www.tiktok.com/@noriak/video/7646862763834281238"}, "format": "download - unknown (watermarked)"}, {"ext": "mp4", "vcodec": "h264", "acodec": "aac", "format_id": "h264_540p_1004559-0", "tbr": 1004, "quality": 1, "preference": -1, "filesize": 4070223, "width": 576, "height": 1024, "url": "https://v16-webapp-prime.us.tiktok.com/video/tos/no1a/tos-no1a-ve-0068c001-no/oEQfZPjIgLA8oRheAUhAe44vIDXmMOPMjBXtY4/?a=1988&bti=ODszNWYuMDE6&&bt=981&ft=aEeq8qT0mIoPD12gdEYI3wU3IBAbMeF~O5&mime_type=video_mp4&rc=MzRlZTo8Zzw2ZTRkOmdkOEBpM21za3k5cm9rOzMzbzczNUBeNS1hYjQyNWExMjVeNjZeYSM0a3AwMmRrbWNhLS1kMTFzcw%3D%3D&expire=1780995292&l=202606070854197D3070279F844563BF08&ply_type=2&policy=2&signature=c5c7e62c10bd073602c282ab3e3a3886&tk=tt_chain_token&btag=e00088000", "protocol": "https", "video_ext": "mp4", "audio_ext": "none", "resolution": "576x1024", "dynamic_range": "SDR", "aspect_ratio": 0.56, "cookies": "ttwid=1%7CJjuPNQnL9us0mldMg1qOGv3JzVsT-DjrHrHAnFblR78%7C1780822459%7C28bf628f30aa8ab8f6602fa0fde3e80c30f7ff8b5a938c9d2b2cdcb25f3a432c; Domain=.tiktok.com; Path=/; Secure; Expires=1811926459; tt_csrf_token=dBth9Rgj-luKI95LCZNJRQ-L1VI5_tl_MLZ8; Domain=.tiktok.com; Path=/; Secure; tt_chain_token=\"MTliXtHu0wXJFnObCfPdhg==\"; Domain=.tiktok.com; Path=/; Secure; Expires=1796374460", "http_headers": {"User-Agent": "Mozilla/5.0 (Windows NT 10.0; Win64; x64) AppleWebKit/537.36 (KHTML, like Gecko) Chrome/141.0.0.0 Safari/537.36", "Accept": "text/html,application/xhtml+xml,application/xml;q=0.9,*/*;q=0.8", "Accept-Language": "en-us,en;q=0.5", "Sec-Fetch-Mode": "navigate", "Referer": "https://www.tiktok.com/@noriak/video/7646862763834281238"}, "format": "h264_540p_1004559-0 - 576x1024"}, {"ext": "mp4", "vcodec": "h264", "acodec": "aac", "format_id": "h264_540p_1004559-1", "tbr": 1004, "quality": 1, "preference": -1, "filesize": 4070223, "width": 576, "height": 1024, "url": "https://v19-webapp-prime.us.tiktok.com/video/tos/no1a/tos-no1a-ve-0068c001-no/oEQfZPjIgLA8oRheAUhAe44vIDXmMOPMjBXtY4/?a=1988&bti=ODszNWYuMDE6&&bt=981&ft=aEeq8qT0mIoPD12gdEYI3wU3IBAbMeF~O5&mime_type=video_mp4&rc=MzRlZTo8Zzw2ZTRkOmdkOEBpM21za3k5cm9rOzMzbzczNUBeNS1hYjQyNWExMjVeNjZeYSM0a3AwMmRrbWNhLS1kMTFzcw%3D%3D&expire=1780995292&l=202606070854197D3070279F844563BF08&ply_type=2&policy=2&signature=c5c7e62c10bd073602c282ab3e3a3886&tk=tt_chain_token&btag=e00088000", "protocol": "https", "video_ext": "mp4", "audio_ext": "none", "resolution": "576x1024", "dynamic_range": "SDR", "aspect_ratio": 0.56, "cookies": "ttwid=1%7CJjuPNQnL9us0mldMg1qOGv3JzVsT-DjrHrHAnFblR78%7C1780822459%7C28bf628f30aa8ab8f6602fa0fde3e80c30f7ff8b5a938c9d2b2cdcb25f3a432c; Domain=.tiktok.com; Path=/; Secure; Expires=1811926459; tt_csrf_token=dBth9Rgj-luKI95LCZNJRQ-L1VI5_tl_MLZ8; Domain=.tiktok.com; Path=/; Secure; tt_chain_token=\"MTliXtHu0wXJFnObCfPdhg==\"; Domain=.tiktok.com; Path=/; Secure; Expires=1796374460", "http_headers": {"User-Agent": "Mozilla/5.0 (Windows NT 10.0; Win64; x64) AppleWebKit/537.36 (KHTML, like Gecko) Chrome/141.0.0.0 Safari/537.36", "Accept": "text/html,application/xhtml+xml,application/xml;q=0.9,*/*;q=0.8", "Accept-Language": "en-us,en;q=0.5", "Sec-Fetch-Mode": "navigate", "Referer": "https://www.tiktok.com/@noriak/video/7646862763834281238"}, "format": "h264_540p_1004559-1 - 576x1024"}, {"ext": "mp4", "vcodec": "h265", "acodec": "aac", "format_id": "bytevc1_540p_388521-0", "tbr": 388, "quality": 1, "preference": -1, "filesize": 1574191, "width": 576, "height": 1024, "url": "https://v16-webapp-prime.us.tiktok.com/video/tos/no1a/tos-no1a-ve-0068-no/ogeMAfmIjtQmPDtUAOgIjHPLVeIluMIILGcDA3/?a=1988&bti=ODszNWYuMDE6&&bt=379&ft=aEeq8qT0mIoPD12gdEYI3wU3IBAbMeF~O5&mime_type=video_mp4&rc=OztnPGhnPDk2NjNoOzQ3NkBpM21za3k5cm9rOzMzbzczNUBfNDVgYjVeNS8xNjQwLjRfYSM0a3AwMmRrbWNhLS1kMTFzcw%3D%3D&expire=1780995292&l=202606070854197D3070279F844563BF08&ply_type=2&policy=2&signature=9e8f8f3b507e63f8992bdbe147bd1cba&tk=tt_chain_token&btag=e00088000", "protocol": "https", "video_ext": "mp4", "audio_ext": "none", "resolution": "576x1024", "dynamic_range": "SDR", "aspect_ratio": 0.56, "cookies": "ttwid=1%7CJjuPNQnL9us0mldMg1qOGv3JzVsT-DjrHrHAnFblR78%7C1780822459%7C28bf628f30aa8ab8f6602fa0fde3e80c30f7ff8b5a938c9d2b2cdcb25f3a432c; Domain=.tiktok.com; Path=/; Secure; Expires=1811926459; tt_csrf_token=dBth9Rgj-luKI95LCZNJRQ-L1VI5_tl_MLZ8; Domain=.tiktok.com; Path=/; Secure; tt_chain_token=\"MTliXtHu0wXJFnObCfPdhg==\"; Domain=.tiktok.com; Path=/; Secure; Expires=1796374460", "http_headers": {"User-Agent": "Mozilla/5.0 (Windows NT 10.0; Win64; x64) AppleWebKit/537.36 (KHTML, like Gecko) Chrome/141.0.0.0 Safari/537.36", "Accept": "text/html,application/xhtml+xml,application/xml;q=0.9,*/*;q=0.8", "Accept-Language": "en-us,en;q=0.5", "Sec-Fetch-Mode": "navigate", "Referer": "https://www.tiktok.com/@noriak/video/7646862763834281238"}, "format": "bytevc1_540p_388521-0 - 576x1024"}, {"ext": "mp4", "vcodec": "h265", "acodec": "aac", "format_id": "bytevc1_540p_388521-1", "tbr": 388, "quality": 1, "preference": -1, "filesize": 1574191, "width": 576, "height": 1024, "url": "https://v19-webapp-prime.us.tiktok.com/video/tos/no1a/tos-no1a-ve-0068-no/ogeMAfmIjtQmPDtUAOgIjHPLVeIluMIILGcDA3/?a=1988&bti=ODszNWYuMDE6&&bt=379&ft=aEeq8qT0mIoPD12gdEYI3wU3IBAbMeF~O5&mime_type=video_mp4&rc=OztnPGhnPDk2NjNoOzQ3NkBpM21za3k5cm9rOzMzbzczNUBfNDVgYjVeNS8xNjQwLjRfYSM0a3AwMmRrbWNhLS1kMTFzcw%3D%3D&expire=1780995292&l=202606070854197D3070279F844563BF08&ply_type=2&policy=2&signature=9e8f8f3b507e63f8992bdbe147bd1cba&tk=tt_chain_token&btag=e00088000", "protocol": "https", "video_ext": "mp4", "audio_ext": "none", "resolution": "576x1024", "dynamic_range": "SDR", "aspect_ratio": 0.56, "cookies": "ttwid=1%7CJjuPNQnL9us0mldMg1qOGv3JzVsT-DjrHrHAnFblR78%7C1780822459%7C28bf628f30aa8ab8f6602fa0fde3e80c30f7ff8b5a938c9d2b2cdcb25f3a432c; Domain=.tiktok.com; Path=/; Secure; Expires=1811926459; tt_csrf_token=dBth9Rgj-luKI95LCZNJRQ-L1VI5_tl_MLZ8; Domain=.tiktok.com; Path=/; Secure; tt_chain_token=\"MTliXtHu0wXJFnObCfPdhg==\"; Domain=.tiktok.com; Path=/; Secure; Expires=1796374460", "http_headers": {"User-Agent": "Mozilla/5.0 (Windows NT 10.0; Win64; x64) AppleWebKit/537.36 (KHTML, like Gecko) Chrome/141.0.0.0 Safari/537.36", "Accept": "text/html,application/xhtml+xml,application/xml;q=0.9,*/*;q=0.8", "Accept-Language": "en-us,en;q=0.5", "Sec-Fetch-Mode": "navigate", "Referer": "https://www.tiktok.com/@noriak/video/7646862763834281238"}, "format": "bytevc1_540p_388521-1 - 576x1024"}, {"ext": "mp4", "vcodec": "h265", "acodec": "aac", "format_id": "bytevc1_720p_470092-0", "tbr": 470, "quality": 2, "preference": -1, "filesize": 1904696, "width": 720, "height": 1280, "url": "https://v16-webapp-prime.us.tiktok.com/video/tos/no1a/tos-no1a-ve-0068c001-no/oUvIvBXPMgM0t4AAm4RA8eQ4UeRejCZLIHbjPD/?a=1988&bti=ODszNWYuMDE6&&bt=459&ft=aEeq8qT0mIoPD12gdEYI3wU3IBAbMeF~O5&mime_type=video_mp4&rc=ZzRnZjc3ZztkZDc4OWQ5NEBpM21za3k5cm9rOzMzbzczNUBjMF8zX2AyNi8xYC4uMzViYSM0a3AwMmRrbWNhLS1kMTFzcw%3D%3D&expire=1780995292&l=202606070854197D3070279F844563BF08&ply_type=2&policy=2&signature=84dc1495daa8c32a43698e6f1cbe51bf&tk=tt_chain_token&btag=e00088000", "protocol": "https", "video_ext": "mp4", "audio_ext": "none", "resolution": "720x1280", "dynamic_range": "SDR", "aspect_ratio": 0.56, "cookies": "ttwid=1%7CJjuPNQnL9us0mldMg1qOGv3JzVsT-DjrHrHAnFblR78%7C1780822459%7C28bf628f30aa8ab8f6602fa0fde3e80c30f7ff8b5a938c9d2b2cdcb25f3a432c; Domain=.tiktok.com; Path=/; Secure; Expires=1811926459; tt_csrf_token=dBth9Rgj-luKI95LCZNJRQ-L1VI5_tl_MLZ8; Domain=.tiktok.com; Path=/; Secure; tt_chain_token=\"MTliXtHu0wXJFnObCfPdhg==\"; Domain=.tiktok.com; Path=/; Secure; Expires=1796374460", "http_headers": {"User-Agent": "Mozilla/5.0 (Windows NT 10.0; Win64; x64) AppleWebKit/537.36 (KHTML, like Gecko) Chrome/141.0.0.0 Safari/537.36", "Accept": "text/html,application/xhtml+xml,application/xml;q=0.9,*/*;q=0.8", "Accept-Language": "en-us,en;q=0.5", "Sec-Fetch-Mode": "navigate", "Referer": "https://www.tiktok.com/@noriak/video/7646862763834281238"}, "format": "bytevc1_720p_470092-0 - 720x1280"}, {"ext": "mp4", "vcodec": "h265", "acodec": "aac", "format_id": "bytevc1_720p_470092-1", "tbr": 470, "quality": 2, "preference": -1, "filesize": 1904696, "width": 720, "height": 1280, "url": "https://v19-webapp-prime.us.tiktok.com/video/tos/no1a/tos-no1a-ve-0068c001-no/oUvIvBXPMgM0t4AAm4RA8eQ4UeRejCZLIHbjPD/?a=1988&bti=ODszNWYuMDE6&&bt=459&ft=aEeq8qT0mIoPD12gdEYI3wU3IBAbMeF~O5&mime_type=video_mp4&rc=ZzRnZjc3ZztkZDc4OWQ5NEBpM21za3k5cm9rOzMzbzczNUBjMF8zX2AyNi8xYC4uMzViYSM0a3AwMmRrbWNhLS1kMTFzcw%3D%3D&expire=1780995292&l=202606070854197D3070279F844563BF08&ply_type=2&policy=2&signature=84dc1495daa8c32a43698e6f1cbe51bf&tk=tt_chain_token&btag=e00088000", "protocol": "https", "video_ext": "mp4", "audio_ext": "none", "resolution": "720x1280", "dynamic_range": "SDR", "aspect_ratio": 0.56, "cookies": "ttwid=1%7CJjuPNQnL9us0mldMg1qOGv3JzVsT-DjrHrHAnFblR78%7C1780822459%7C28bf628f30aa8ab8f6602fa0fde3e80c30f7ff8b5a938c9d2b2cdcb25f3a432c; Domain=.tiktok.com; Path=/; Secure; Expires=1811926459; tt_csrf_token=dBth9Rgj-luKI95LCZNJRQ-L1VI5_tl_MLZ8; Domain=.tiktok.com; Path=/; Secure; tt_chain_token=\"MTliXtHu0wXJFnObCfPdhg==\"; Domain=.tiktok.com; Path=/; Secure; Expires=1796374460", "http_headers": {"User-Agent": "Mozilla/5.0 (Windows NT 10.0; Win64; x64) AppleWebKit/537.36 (KHTML, like Gecko) Chrome/141.0.0.0 Safari/537.36", "Accept": "text/html,application/xhtml+xml,application/xml;q=0.9,*/*;q=0.8", "Accept-Language": "en-us,en;q=0.5", "Sec-Fetch-Mode": "navigate", "Referer": "https://www.tiktok.com/@noriak/video/7646862763834281238"}, "format": "bytevc1_720p_470092-1 - 720x1280"}, {"ext": "mp4", "vcodec": "h265", "acodec": "aac", "format_id": "bytevc1_1080p_823505-0", "tbr": 823, "quality": 3, "preference": -1, "filesize": 3336637, "width": 1080, "height": 1920, "url": "https://v16-webapp-prime.us.tiktok.com/video/tos/no1a/tos-no1a-ve-0068c001-no/oYQXfU3I7DjGiAjPeMIAQLILmIG9mPgROectCI/?a=1988&bti=ODszNWYuMDE6&&bt=804&ft=aEeq8qT0mIoPD12gdEYI3wU3IBAbMeF~O5&mime_type=video_mp4&rc=aTRmNzxnO2Y3NjM5NDwzN0BpM21za3k5cm9rOzMzbzczNUBeYGM0MGA2NTYxYGAtYmNjYSM0a3AwMmRrbWNhLS1kMTFzcw%3D%3D&expire=1780995292&l=202606070854197D3070279F844563BF08&ply_type=2&policy=2&signature=4c1843fbd499beb93fb80db368c9a20e&tk=tt_chain_token&btag=e00088000", "protocol": "https", "video_ext": "mp4", "audio_ext": "none", "resolution": "1080x1920", "dynamic_range": "SDR", "aspect_ratio": 0.56, "cookies": "ttwid=1%7CJjuPNQnL9us0mldMg1qOGv3JzVsT-DjrHrHAnFblR78%7C1780822459%7C28bf628f30aa8ab8f6602fa0fde3e80c30f7ff8b5a938c9d2b2cdcb25f3a432c; Domain=.tiktok.com; Path=/; Secure; Expires=1811926459; tt_csrf_token=dBth9Rgj-luKI95LCZNJRQ-L1VI5_tl_MLZ8; Domain=.tiktok.com; Path=/; Secure; tt_chain_token=\"MTliXtHu0wXJFnObCfPdhg==\"; Domain=.tiktok.com; Path=/; Secure; Expires=1796374460", "http_headers": {"User-Agent": "Mozilla/5.0 (Windows NT 10.0; Win64; x64) AppleWebKit/537.36 (KHTML, like Gecko) Chrome/141.0.0.0 Safari/537.36", "Accept": "text/html,application/xhtml+xml,application/xml;q=0.9,*/*;q=0.8", "Accept-Language": "en-us,en;q=0.5", "Sec-Fetch-Mode": "navigate", "Referer": "https://www.tiktok.com/@noriak/video/7646862763834281238"}, "format": "bytevc1_1080p_823505-0 - 1080x1920"}, {"ext": "mp4", "vcodec": "h265", "acodec": "aac", "format_id": "bytevc1_1080p_823505-1", "tbr": 823, "quality": 3, "preference": -1, "filesize": 3336637, "width": 1080, "height": 1920, "url": "https://v19-webapp-prime.us.tiktok.com/video/tos/no1a/tos-no1a-ve-0068c001-no/oYQXfU3I7DjGiAjPeMIAQLILmIG9mPgROectCI/?a=1988&bti=ODszNWYuMDE6&&bt=804&ft=aEeq8qT0mIoPD12gdEYI3wU3IBAbMeF~O5&mime_type=video_mp4&rc=aTRmNzxnO2Y3NjM5NDwzN0BpM21za3k5cm9rOzMzbzczNUBeYGM0MGA2NTYxYGAtYmNjYSM0a3AwMmRrbWNhLS1kMTFzcw%3D%3D&expire=1780995292&l=202606070854197D3070279F844563BF08&ply_type=2&policy=2&signature=4c1843fbd499beb93fb80db368c9a20e&tk=tt_chain_token&btag=e00088000", "protocol": "https", "video_ext": "mp4", "audio_ext": "none", "resolution": "1080x1920", "dynamic_range": "SDR", "aspect_ratio": 0.56, "cookies": "ttwid=1%7CJjuPNQnL9us0mldMg1qOGv3JzVsT-DjrHrHAnFblR78%7C1780822459%7C28bf628f30aa8ab8f6602fa0fde3e80c30f7ff8b5a938c9d2b2cdcb25f3a432c; Domain=.tiktok.com; Path=/; Secure; Expires=1811926459; tt_csrf_token=dBth9Rgj-luKI95LCZNJRQ-L1VI5_tl_MLZ8; Domain=.tiktok.com; Path=/; Secure; tt_chain_token=\"MTliXtHu0wXJFnObCfPdhg==\"; Domain=.tiktok.com; Path=/; Secure; Expires=1796374460", "http_headers": {"User-Agent": "Mozilla/5.0 (Windows NT 10.0; Win64; x64) AppleWebKit/537.36 (KHTML, like Gecko) Chrome/141.0.0.0 Safari/537.36", "Accept": "text/html,application/xhtml+xml,application/xml;q=0.9,*/*;q=0.8", "Accept-Language": "en-us,en;q=0.5", "Sec-Fetch-Mode": "navigate", "Referer": "https://www.tiktok.com/@noriak/video/7646862763834281238"}, "format": "bytevc1_1080p_823505-1 - 1080x1920"}], "subtitles": {}, "http_headers": {"User-Agent": "Mozilla/5.0 (Windows NT 10.0; Win64; x64) AppleWebKit/537.36 (KHTML, like Gecko) Chrome/141.0.0.0 Safari/537.36", "Accept": "text/html,application/xhtml+xml,application/xml;q=0.9,*/*;q=0.8", "Accept-Language": "en-us,en;q=0.5", "Sec-Fetch-Mode": "navigate", "Referer": "https://www.tiktok.com/@noriak/video/7646862763834281238"}, "channel": "Nori&Ak", "channel_id": "MS4wLjABAAAAFW6-_uPYJd7dVIkTysfPX7Wxz20BhTqY41A9hksWeWR51Ci7FA-NCh236bPOLPVv", "uploader": "noriak", "uploader_id": "7642044968437613590", "channel_url": "https://www.tiktok.com/@MS4wLjABAAAAFW6-_uPYJd7dVIkTysfPX7Wxz20BhTqY41A9hksWeWR51Ci7FA-NCh236bPOLPVv", "uploader_url": "https://www.tiktok.com/@noriak", "track": "original sound", "artists": ["Nori&Ak"], "duration": 32, "title": "#fyp ", "description": "#fyp ", "timestamp": 1780423987, "view_count": 7677, "like_count": 645, "repost_count": 263, "comment_count": 25, "save_count": 48, "thumbnails": [{"id": "dynamicCover", "url": "https://p19-common-sign.tiktokcdn-us.com/tos-no1a-p-0037-no/oEeLrmUgeeMM3DZOAtImj8QUXIAjhFP464v4ag~tplv-tiktokx-origin.image?dr=9636&x-expires=1780992000&x-signature=iqN%2FR8UUQ9yyLHa0m%2FkW7fN6fJI%3D&t=4d5b0474&ps=13740610&shp=81f88b70&shcp=43f4a2f9&idc=useast8", "preference": -2}, {"id": "cover", "url": "https://p19-common-sign.tiktokcdn-us.com/tos-no1a-p-0037-no/oI8ZeetALKDQuvA44zMMIUgmPgTm1OjxjX4IRe~tplv-tiktokx-origin.image?dr=9636&x-expires=1780992000&x-signature=xvWIA%2B3QO3c4KcBUs7idCZDz%2FT8%3D&t=4d5b0474&ps=13740610&shp=81f88b70&shcp=43f4a2f9&idc=useast8", "preference": -1}, {"id": "originCover", "url": "https://p19-common-sign.tiktokcdn-us.com/tos-no1a-p-0037-no/oce44XDjIMURPZImOAdeAbmvg8Mt4pLQejgFjE~tplv-tiktokx-origin.image?dr=9636&x-expires=1780992000&x-signature=2jUINuCczom5Zcl104Tp1pX6Yjo%3D&t=4d5b0474&ps=13740610&shp=81f88b70&shcp=43f4a2f9&idc=useast8", "preference": -1}], "webpage_url": "https://www.tiktok.com/@noriak/video/7646862763834281238", "webpage_url_basename": "7646862763834281238", "webpage_url_domain": "tiktok.com", "extractor": "TikTok", "extractor_key": "TikTok", "thumbnail": "https://p19-common-sign.tiktokcdn-us.com/tos-no1a-p-0037-no/oce44XDjIMURPZImOAdeAbmvg8Mt4pLQejgFjE~tplv-tiktokx-origin.image?dr=9636&x-expires=1780992000&x-signature=2jUINuCczom5Zcl104Tp1pX6Yjo%3D&t=4d5b0474&ps=13740610&shp=81f88b70&shcp=43f4a2f9&idc=useast8", "display_id": "7646862763834281238", "fulltitle": "#fyp ", "duration_string": "32", "upload_date": "20260602", "artist": "Nori&Ak", "epoch": 1780822460, "ext": "mp4", "vcodec": "h265", "acodec": "aac", "format_id": "bytevc1_1080p_823505-1", "tbr": 823, "quality": 3, "preference": -1, "filesize": 3336637, "width": 1080, "height": 1920, "url": "https://v19-webapp-prime.us.tiktok.com/video/tos/no1a/tos-no1a-ve-0068c001-no/oYQXfU3I7DjGiAjPeMIAQLILmIG9mPgROectCI/?a=1988&bti=ODszNWYuMDE6&&bt=804&ft=aEeq8qT0mIoPD12gdEYI3wU3IBAbMeF~O5&mime_type=video_mp4&rc=aTRmNzxnO2Y3NjM5NDwzN0BpM21za3k5cm9rOzMzbzczNUBeYGM0MGA2NTYxYGAtYmNjYSM0a3AwMmRrbWNhLS1kMTFzcw%3D%3D&expire=1780995292&l=202606070854197D3070279F844563BF08&ply_type=2&policy=2&signature=4c1843fbd499beb93fb80db368c9a20e&tk=tt_chain_token&btag=e00088000", "protocol": "https", "video_ext": "mp4", "audio_ext": "none", "resolution": "1080x1920", "dynamic_range": "SDR", "aspect_ratio": 0.56, "cookies": "ttwid=1%7CJjuPNQnL9us0mldMg1qOGv3JzVsT-DjrHrHAnFblR78%7C1780822459%7C28bf628f30aa8ab8f6602fa0fde3e80c30f7ff8b5a938c9d2b2cdcb25f3a432c; Domain=.tiktok.com; Path=/; Secure; Expires=1811926459; tt_csrf_token=dBth9Rgj-luKI95LCZNJRQ-L1VI5_tl_MLZ8; Domain=.tiktok.com; Path=/; Secure; tt_chain_token=\"MTliXtHu0wXJFnObCfPdhg==\"; Domain=.tiktok.com; Path=/; Secure; Expires=1796374460", "format": "bytevc1_1080p_823505-1 - 1080x1920", "_type": "video", "_version": {"version": "2026.03.17", "release_git_head": "04d6974f502bbdfaed72c624344f262e30ad9708", "repository": "yt-dlp/yt-dlp"}}