{"id": "7382967406362103086", "formats": [{"ext": "mp4", "vcodec": "h264", "acodec": "aac", "format_id": "download", "url": "https://v16-webapp-prime.us.tiktok.com/video/tos/useast5/tos-useast5-pve-0068-tx/oExQ8vhTDDId3SgrUYFDgGIERAoEgeCfEKBmNZ/?a=1988&bti=ODszNWYuMDE6&&bt=1042&ft=4KJMyMzm8Zmo06ebha4jVczjQpWrKsd.&mime_type=video_mp4&rc=NDo2NjRkNDVnM2VnOWVpOEBpM2ppZG45cjNzczMzZzczNEAuM2BfYzM1X2AxXjJhLmFgYSNqLWNgMmRrMG5gLS1kMS9zcw%3D%3D&expire=1782208088&l=2026062109472840F92B237B7DD5D01BE3&ply_type=2&policy=2&signature=f4667b43849d8e33bd987989f41e0a2a&tk=tt_chain_token&btag=e00088000", "format_note": "watermarked", "preference": -2, "protocol": "https", "video_ext": "mp4", "audio_ext": "none", "dynamic_range": "SDR", "cookies": "ttwid=1%7C9A286D27vKc5mZtjIupHnDeXatyoXthru3_qe9hop_o%7C1782035248%7Cf3067fb3795e2a40e15cf65689b1a3b74a7cbc2f114772db410be2b4eef481e6; Domain=.tiktok.com; Path=/; Secure; Expires=1813139248; tt_csrf_token=4NOQFKCI-wp-v3R1qmZPgWFl86NGszBk2gp8; Domain=.tiktok.com; Path=/; Secure; tt_chain_token=\"8R9F5Mqm/wLsbHNgs9efgg==\"; Domain=.tiktok.com; Path=/; Secure; Expires=1797587248", "http_headers": {"User-Agent": "Mozilla/5.0 (Windows NT 10.0; Win64; x64) AppleWebKit/537.36 (KHTML, like Gecko) Chrome/147.0.0.0 Safari/537.36", "Accept": "text/html,application/xhtml+xml,application/xml;q=0.9,*/*;q=0.8", "Accept-Language": "en-us,en;q=0.5", "Sec-Fetch-Mode": "navigate", "Referer": "https://www.tiktok.com/@johnnnyhuynh/video/7382967406362103086"}, "format": "download - unknown (watermarked)"}, {"ext": "mp4", "vcodec": "h264", "acodec": "aac", "format_id": "h264_540p_354410-0", "tbr": 354, "quality": 1, "preference": -1, "filesize": 1775462, "width": 576, "height": 1024, "url": "https://v16-webapp-prime.us.tiktok.com/video/tos/useast5/tos-useast5-ve-0068c003-tx/o02vpIggYE4ssQUV08BRsAoiBn7WZBkciQwE1/?a=1988&bti=ODszNWYuMDE6&&bt=346&ft=4KJMyMzm8Zmo06ebha4jVczjQpWrKsd.&mime_type=video_mp4&rc=aDlnNzVmOzg6OTQ1ZzU3OEBpM2ppZG45cjNzczMzZzczNEBjNDMzM2I1NWAxLTFjX18tYSNqLWNgMmRrMG5gLS1kMS9zcw%3D%3D&expire=1782208088&l=2026062109472840F92B237B7DD5D01BE3&ply_type=2&policy=2&signature=1ab99dd989f67358261c945fe79a4f4b&tk=tt_chain_token&btag=e00088000", "protocol": "https", "video_ext": "mp4", "audio_ext": "none", "resolution": "576x1024", "dynamic_range": "SDR", "aspect_ratio": 0.56, "cookies": "ttwid=1%7C9A286D27vKc5mZtjIupHnDeXatyoXthru3_qe9hop_o%7C1782035248%7Cf3067fb3795e2a40e15cf65689b1a3b74a7cbc2f114772db410be2b4eef481e6; Domain=.tiktok.com; Path=/; Secure; Expires=1813139248; tt_csrf_token=4NOQFKCI-wp-v3R1qmZPgWFl86NGszBk2gp8; Domain=.tiktok.com; Path=/; Secure; tt_chain_token=\"8R9F5Mqm/wLsbHNgs9efgg==\"; Domain=.tiktok.com; Path=/; Secure; Expires=1797587248", "http_headers": {"User-Agent": "Mozilla/5.0 (Windows NT 10.0; Win64; x64) AppleWebKit/537.36 (KHTML, like Gecko) Chrome/147.0.0.0 Safari/537.36", "Accept": "text/html,application/xhtml+xml,application/xml;q=0.9,*/*;q=0.8", "Accept-Language": "en-us,en;q=0.5", "Sec-Fetch-Mode": "navigate", "Referer": "https://www.tiktok.com/@johnnnyhuynh/video/7382967406362103086"}, "format": "h264_540p_354410-0 - 576x1024"}, {"ext": "mp4", "vcodec": "h264", "acodec": "aac", "format_id": "h264_540p_354410-1", "tbr": 354, "quality": 1, "preference": -1, "filesize": 1775462, "width": 576, "height": 1024, "url": "https://v19-webapp-prime.us.tiktok.com/video/tos/useast5/tos-useast5-ve-0068c003-tx/o02vpIggYE4ssQUV08BRsAoiBn7WZBkciQwE1/?a=1988&bti=ODszNWYuMDE6&&bt=346&ft=4KJMyMzm8Zmo06ebha4jVczjQpWrKsd.&mime_type=video_mp4&rc=aDlnNzVmOzg6OTQ1ZzU3OEBpM2ppZG45cjNzczMzZzczNEBjNDMzM2I1NWAxLTFjX18tYSNqLWNgMmRrMG5gLS1kMS9zcw%3D%3D&expire=1782208088&l=2026062109472840F92B237B7DD5D01BE3&ply_type=2&policy=2&signature=1ab99dd989f67358261c945fe79a4f4b&tk=tt_chain_token&btag=e00088000", "protocol": "https", "video_ext": "mp4", "audio_ext": "none", "resolution": "576x1024", "dynamic_range": "SDR", "aspect_ratio": 0.56, "cookies": "ttwid=1%7C9A286D27vKc5mZtjIupHnDeXatyoXthru3_qe9hop_o%7C1782035248%7Cf3067fb3795e2a40e15cf65689b1a3b74a7cbc2f114772db410be2b4eef481e6; Domain=.tiktok.com; Path=/; Secure; Expires=1813139248; tt_csrf_token=4NOQFKCI-wp-v3R1qmZPgWFl86NGszBk2gp8; Domain=.tiktok.com; Path=/; Secure; tt_chain_token=\"8R9F5Mqm/wLsbHNgs9efgg==\"; Domain=.tiktok.com; Path=/; Secure; Expires=1797587248", "http_headers": {"User-Agent": "Mozilla/5.0 (Windows NT 10.0; Win64; x64) AppleWebKit/537.36 (KHTML, like Gecko) Chrome/147.0.0.0 Safari/537.36", "Accept": "text/html,application/xhtml+xml,application/xml;q=0.9,*/*;q=0.8", "Accept-Language": "en-us,en;q=0.5", "Sec-Fetch-Mode": "navigate", "Referer": "https://www.tiktok.com/@johnnnyhuynh/video/7382967406362103086"}, "format": "h264_540p_354410-1 - 576x1024"}, {"ext": "mp4", "vcodec": "h264", "acodec": "aac", "format_id": "h264_540p_959856-0", "tbr": 959, "quality": 1, "preference": -1, "filesize": 4808519, "width": 576, "height": 1024, "url": "https://v16-webapp-prime.us.tiktok.com/video/tos/useast5/tos-useast5-ve-0068c001-tx/oYK3IZMxDI76YroGAgFgSORChBfGmJDQEfgTEd/?a=1988&bti=ODszNWYuMDE6&&bt=937&ft=4KJMyMzm8Zmo06ebha4jVczjQpWrKsd.&mime_type=video_mp4&rc=N2c2Nmk6ZTVpaDM6NDo6M0BpM2ppZG45cjNzczMzZzczNEAxYzVgMzQxXy8xMzYtMi00YSNqLWNgMmRrMG5gLS1kMS9zcw%3D%3D&expire=1782208088&l=2026062109472840F92B237B7DD5D01BE3&ply_type=2&policy=2&signature=2f3422167228dda4e736d49775d7d748&tk=tt_chain_token&btag=e00088000", "protocol": "https", "video_ext": "mp4", "audio_ext": "none", "resolution": "576x1024", "dynamic_range": "SDR", "aspect_ratio": 0.56, "cookies": "ttwid=1%7C9A286D27vKc5mZtjIupHnDeXatyoXthru3_qe9hop_o%7C1782035248%7Cf3067fb3795e2a40e15cf65689b1a3b74a7cbc2f114772db410be2b4eef481e6; Domain=.tiktok.com; Path=/; Secure; Expires=1813139248; tt_csrf_token=4NOQFKCI-wp-v3R1qmZPgWFl86NGszBk2gp8; Domain=.tiktok.com; Path=/; Secure; tt_chain_token=\"8R9F5Mqm/wLsbHNgs9efgg==\"; Domain=.tiktok.com; Path=/; Secure; Expires=1797587248", "http_headers": {"User-Agent": "Mozilla/5.0 (Windows NT 10.0; Win64; x64) AppleWebKit/537.36 (KHTML, like Gecko) Chrome/147.0.0.0 Safari/537.36", "Accept": "text/html,application/xhtml+xml,application/xml;q=0.9,*/*;q=0.8", "Accept-Language": "en-us,en;q=0.5", "Sec-Fetch-Mode": "navigate", "Referer": "https://www.tiktok.com/@johnnnyhuynh/video/7382967406362103086"}, "format": "h264_540p_959856-0 - 576x1024"}, {"ext": "mp4", "vcodec": "h264", "acodec": "aac", "format_id": "h264_540p_959856-1", "tbr": 959, "quality": 1, "preference": -1, "filesize": 4808519, "width": 576, "height": 1024, "url": "https://v19-webapp-prime.us.tiktok.com/video/tos/useast5/tos-useast5-ve-0068c001-tx/oYK3IZMxDI76YroGAgFgSORChBfGmJDQEfgTEd/?a=1988&bti=ODszNWYuMDE6&&bt=937&ft=4KJMyMzm8Zmo06ebha4jVczjQpWrKsd.&mime_type=video_mp4&rc=N2c2Nmk6ZTVpaDM6NDo6M0BpM2ppZG45cjNzczMzZzczNEAxYzVgMzQxXy8xMzYtMi00YSNqLWNgMmRrMG5gLS1kMS9zcw%3D%3D&expire=1782208088&l=2026062109472840F92B237B7DD5D01BE3&ply_type=2&policy=2&signature=2f3422167228dda4e736d49775d7d748&tk=tt_chain_token&btag=e00088000", "protocol": "https", "video_ext": "mp4", "audio_ext": "none", "resolution": "576x1024", "dynamic_range": "SDR", "aspect_ratio": 0.56, "cookies": "ttwid=1%7C9A286D27vKc5mZtjIupHnDeXatyoXthru3_qe9hop_o%7C1782035248%7Cf3067fb3795e2a40e15cf65689b1a3b74a7cbc2f114772db410be2b4eef481e6; Domain=.tiktok.com; Path=/; Secure; Expires=1813139248; tt_csrf_token=4NOQFKCI-wp-v3R1qmZPgWFl86NGszBk2gp8; Domain=.tiktok.com; Path=/; Secure; tt_chain_token=\"8R9F5Mqm/wLsbHNgs9efgg==\"; Domain=.tiktok.com; Path=/; Secure; Expires=1797587248", "http_headers": {"User-Agent": "Mozilla/5.0 (Windows NT 10.0; Win64; x64) AppleWebKit/537.36 (KHTML, like Gecko) Chrome/147.0.0.0 Safari/537.36", "Accept": "text/html,application/xhtml+xml,application/xml;q=0.9,*/*;q=0.8", "Accept-Language": "en-us,en;q=0.5", "Sec-Fetch-Mode": "navigate", "Referer": "https://www.tiktok.com/@johnnnyhuynh/video/7382967406362103086"}, "format": "h264_540p_959856-1 - 576x1024"}, {"ext": "mp4", "vcodec": "h265", "acodec": "aac", "format_id": "bytevc1_540p_387127-0", "tbr": 387, "quality": 1, "preference": -1, "filesize": 1939411, "width": 576, "height": 1024, "url": "https://v16-webapp-prime.us.tiktok.com/video/tos/useast5/tos-useast5-pve-0068-tx/oIsBE4g0FipQk21UhWZhv0tRVnEQBiYIw7gBA/?a=1988&bti=ODszNWYuMDE6&&bt=378&ft=4KJMyMzm8Zmo06ebha4jVczjQpWrKsd.&mime_type=video_mp4&rc=ZTQ2N2Q6Nmc3OjM7ZzczNEBpM2ppZG45cjNzczMzZzczNEA2L2AzMS1fNWMxMDNfNjI2YSNqLWNgMmRrMG5gLS1kMS9zcw%3D%3D&expire=1782208088&l=2026062109472840F92B237B7DD5D01BE3&ply_type=2&policy=2&signature=90bd81513628f084355817427b463410&tk=tt_chain_token&btag=e00088000", "protocol": "https", "video_ext": "mp4", "audio_ext": "none", "resolution": "576x1024", "dynamic_range": "SDR", "aspect_ratio": 0.56, "cookies": "ttwid=1%7C9A286D27vKc5mZtjIupHnDeXatyoXthru3_qe9hop_o%7C1782035248%7Cf3067fb3795e2a40e15cf65689b1a3b74a7cbc2f114772db410be2b4eef481e6; Domain=.tiktok.com; Path=/; Secure; Expires=1813139248; tt_csrf_token=4NOQFKCI-wp-v3R1qmZPgWFl86NGszBk2gp8; Domain=.tiktok.com; Path=/; Secure; tt_chain_token=\"8R9F5Mqm/wLsbHNgs9efgg==\"; Domain=.tiktok.com; Path=/; Secure; Expires=1797587248", "http_headers": {"User-Agent": "Mozilla/5.0 (Windows NT 10.0; Win64; x64) AppleWebKit/537.36 (KHTML, like Gecko) Chrome/147.0.0.0 Safari/537.36", "Accept": "text/html,application/xhtml+xml,application/xml;q=0.9,*/*;q=0.8", "Accept-Language": "en-us,en;q=0.5", "Sec-Fetch-Mode": "navigate", "Referer": "https://www.tiktok.com/@johnnnyhuynh/video/7382967406362103086"}, "format": "bytevc1_540p_387127-0 - 576x1024"}, {"ext": "mp4", "vcodec": "h265", "acodec": "aac", "format_id": "bytevc1_540p_387127-1", "tbr": 387, "quality": 1, "preference": -1, "filesize": 1939411, "width": 576, "height": 1024, "url": "https://v19-webapp-prime.us.tiktok.com/video/tos/useast5/tos-useast5-pve-0068-tx/oIsBE4g0FipQk21UhWZhv0tRVnEQBiYIw7gBA/?a=1988&bti=ODszNWYuMDE6&&bt=378&ft=4KJMyMzm8Zmo06ebha4jVczjQpWrKsd.&mime_type=video_mp4&rc=ZTQ2N2Q6Nmc3OjM7ZzczNEBpM2ppZG45cjNzczMzZzczNEA2L2AzMS1fNWMxMDNfNjI2YSNqLWNgMmRrMG5gLS1kMS9zcw%3D%3D&expire=1782208088&l=2026062109472840F92B237B7DD5D01BE3&ply_type=2&policy=2&signature=90bd81513628f084355817427b463410&tk=tt_chain_token&btag=e00088000", "protocol": "https", "video_ext": "mp4", "audio_ext": "none", "resolution": "576x1024", "dynamic_range": "SDR", "aspect_ratio": 0.56, "cookies": "ttwid=1%7C9A286D27vKc5mZtjIupHnDeXatyoXthru3_qe9hop_o%7C1782035248%7Cf3067fb3795e2a40e15cf65689b1a3b74a7cbc2f114772db410be2b4eef481e6; Domain=.tiktok.com; Path=/; Secure; Expires=1813139248; tt_csrf_token=4NOQFKCI-wp-v3R1qmZPgWFl86NGszBk2gp8; Domain=.tiktok.com; Path=/; Secure; tt_chain_token=\"8R9F5Mqm/wLsbHNgs9efgg==\"; Domain=.tiktok.com; Path=/; Secure; Expires=1797587248", "http_headers": {"User-Agent": "Mozilla/5.0 (Windows NT 10.0; Win64; x64) AppleWebKit/537.36 (KHTML, like Gecko) Chrome/147.0.0.0 Safari/537.36", "Accept": "text/html,application/xhtml+xml,application/xml;q=0.9,*/*;q=0.8", "Accept-Language": "en-us,en;q=0.5", "Sec-Fetch-Mode": "navigate", "Referer": "https://www.tiktok.com/@johnnnyhuynh/video/7382967406362103086"}, "format": "bytevc1_540p_387127-1 - 576x1024"}, {"ext": "mp4", "vcodec": "h265", "acodec": "aac", "format_id": "bytevc1_720p_452880-0", "tbr": 452, "quality": 2, "preference": -1, "filesize": 2268818, "width": 720, "height": 1280, "url": "https://v16-webapp-prime.us.tiktok.com/video/tos/useast5/tos-useast5-ve-0068c002-tx/oMgvUdsxzB7n1QRniE4QT0ZkBEICpgYwXiKAW/?a=1988&bti=ODszNWYuMDE6&&bt=442&ft=4KJMyMzm8Zmo06ebha4jVczjQpWrKsd.&mime_type=video_mp4&rc=Zjg6OWhpNTg4O2RnZzdoOUBpM2ppZG45cjNzczMzZzczNEBjMDJhLV9hNjYxMV8wMF9gYSNqLWNgMmRrMG5gLS1kMS9zcw%3D%3D&expire=1782208088&l=2026062109472840F92B237B7DD5D01BE3&ply_type=2&policy=2&signature=8dd570a9db4564de8e770074184a521c&tk=tt_chain_token&btag=e00088000", "protocol": "https", "video_ext": "mp4", "audio_ext": "none", "resolution": "720x1280", "dynamic_range": "SDR", "aspect_ratio": 0.56, "cookies": "ttwid=1%7C9A286D27vKc5mZtjIupHnDeXatyoXthru3_qe9hop_o%7C1782035248%7Cf3067fb3795e2a40e15cf65689b1a3b74a7cbc2f114772db410be2b4eef481e6; Domain=.tiktok.com; Path=/; Secure; Expires=1813139248; tt_csrf_token=4NOQFKCI-wp-v3R1qmZPgWFl86NGszBk2gp8; Domain=.tiktok.com; Path=/; Secure; tt_chain_token=\"8R9F5Mqm/wLsbHNgs9efgg==\"; Domain=.tiktok.com; Path=/; Secure; Expires=1797587248", "http_headers": {"User-Agent": "Mozilla/5.0 (Windows NT 10.0; Win64; x64) AppleWebKit/537.36 (KHTML, like Gecko) Chrome/147.0.0.0 Safari/537.36", "Accept": "text/html,application/xhtml+xml,application/xml;q=0.9,*/*;q=0.8", "Accept-Language": "en-us,en;q=0.5", "Sec-Fetch-Mode": "navigate", "Referer": "https://www.tiktok.com/@johnnnyhuynh/video/7382967406362103086"}, "format": "bytevc1_720p_452880-0 - 720x1280"}, {"ext": "mp4", "vcodec": "h265", "acodec": "aac", "format_id": "bytevc1_720p_452880-1", "tbr": 452, "quality": 2, "preference": -1, "filesize": 2268818, "width": 720, "height": 1280, "url": "https://v19-webapp-prime.us.tiktok.com/video/tos/useast5/tos-useast5-ve-0068c002-tx/oMgvUdsxzB7n1QRniE4QT0ZkBEICpgYwXiKAW/?a=1988&bti=ODszNWYuMDE6&&bt=442&ft=4KJMyMzm8Zmo06ebha4jVczjQpWrKsd.&mime_type=video_mp4&rc=Zjg6OWhpNTg4O2RnZzdoOUBpM2ppZG45cjNzczMzZzczNEBjMDJhLV9hNjYxMV8wMF9gYSNqLWNgMmRrMG5gLS1kMS9zcw%3D%3D&expire=1782208088&l=2026062109472840F92B237B7DD5D01BE3&ply_type=2&policy=2&signature=8dd570a9db4564de8e770074184a521c&tk=tt_chain_token&btag=e00088000", "protocol": "https", "video_ext": "mp4", "audio_ext": "none", "resolution": "720x1280", "dynamic_range": "SDR", "aspect_ratio": 0.56, "cookies": "ttwid=1%7C9A286D27vKc5mZtjIupHnDeXatyoXthru3_qe9hop_o%7C1782035248%7Cf3067fb3795e2a40e15cf65689b1a3b74a7cbc2f114772db410be2b4eef481e6; Domain=.tiktok.com; Path=/; Secure; Expires=1813139248; tt_csrf_token=4NOQFKCI-wp-v3R1qmZPgWFl86NGszBk2gp8; Domain=.tiktok.com; Path=/; Secure; tt_chain_token=\"8R9F5Mqm/wLsbHNgs9efgg==\"; Domain=.tiktok.com; Path=/; Secure; Expires=1797587248", "http_headers": {"User-Agent": "Mozilla/5.0 (Windows NT 10.0; Win64; x64) AppleWebKit/537.36 (KHTML, like Gecko) Chrome/147.0.0.0 Safari/537.36", "Accept": "text/html,application/xhtml+xml,application/xml;q=0.9,*/*;q=0.8", "Accept-Language": "en-us,en;q=0.5", "Sec-Fetch-Mode": "navigate", "Referer": "https://www.tiktok.com/@johnnnyhuynh/video/7382967406362103086"}, "format": "bytevc1_720p_452880-1 - 720x1280"}, {"ext": "mp4", "vcodec": "h265", "acodec": "aac", "format_id": "bytevc1_1080p_654722-0", "tbr": 654, "quality": 3, "preference": -1, "filesize": 3279998, "width": 1080, "height": 1920, "url": "https://v16-webapp-prime.us.tiktok.com/video/tos/useast5/tos-useast5-ve-0068c001-tx/oQDiAUEQ0IBwRk4gQIn0gpNxv7AsWgYBs1ZEi/?a=1988&bti=ODszNWYuMDE6&&bt=639&ft=4KJMyMzm8Zmo06ebha4jVczjQpWrKsd.&mime_type=video_mp4&rc=OzxkOzU4OzdoZ2k3ZDtpNkBpM2ppZG45cjNzczMzZzczNEAxNF5gL2E2NTMxXzRfLl82YSNqLWNgMmRrMG5gLS1kMS9zcw%3D%3D&expire=1782208088&l=2026062109472840F92B237B7DD5D01BE3&ply_type=2&policy=2&signature=ffc17677882e9d38363df6fcf4241d84&tk=tt_chain_token&btag=e00088000", "protocol": "https", "video_ext": "mp4", "audio_ext": "none", "resolution": "1080x1920", "dynamic_range": "SDR", "aspect_ratio": 0.56, "cookies": "ttwid=1%7C9A286D27vKc5mZtjIupHnDeXatyoXthru3_qe9hop_o%7C1782035248%7Cf3067fb3795e2a40e15cf65689b1a3b74a7cbc2f114772db410be2b4eef481e6; Domain=.tiktok.com; Path=/; Secure; Expires=1813139248; tt_csrf_token=4NOQFKCI-wp-v3R1qmZPgWFl86NGszBk2gp8; Domain=.tiktok.com; Path=/; Secure; tt_chain_token=\"8R9F5Mqm/wLsbHNgs9efgg==\"; Domain=.tiktok.com; Path=/; Secure; Expires=1797587248", "http_headers": {"User-Agent": "Mozilla/5.0 (Windows NT 10.0; Win64; x64) AppleWebKit/537.36 (KHTML, like Gecko) Chrome/147.0.0.0 Safari/537.36", "Accept": "text/html,application/xhtml+xml,application/xml;q=0.9,*/*;q=0.8", "Accept-Language": "en-us,en;q=0.5", "Sec-Fetch-Mode": "navigate", "Referer": "https://www.tiktok.com/@johnnnyhuynh/video/7382967406362103086"}, "format": "bytevc1_1080p_654722-0 - 1080x1920"}, {"ext": "mp4", "vcodec": "h265", "acodec": "aac", "format_id": "bytevc1_1080p_654722-1", "tbr": 654, "quality": 3, "preference": -1, "filesize": 3279998, "width": 1080, "height": 1920, "url": "https://v19-webapp-prime.us.tiktok.com/video/tos/useast5/tos-useast5-ve-0068c001-tx/oQDiAUEQ0IBwRk4gQIn0gpNxv7AsWgYBs1ZEi/?a=1988&bti=ODszNWYuMDE6&&bt=639&ft=4KJMyMzm8Zmo06ebha4jVczjQpWrKsd.&mime_type=video_mp4&rc=OzxkOzU4OzdoZ2k3ZDtpNkBpM2ppZG45cjNzczMzZzczNEAxNF5gL2E2NTMxXzRfLl82YSNqLWNgMmRrMG5gLS1kMS9zcw%3D%3D&expire=1782208088&l=2026062109472840F92B237B7DD5D01BE3&ply_type=2&policy=2&signature=ffc17677882e9d38363df6fcf4241d84&tk=tt_chain_token&btag=e00088000", "protocol": "https", "video_ext": "mp4", "audio_ext": "none", "resolution": "1080x1920", "dynamic_range": "SDR", "aspect_ratio": 0.56, "cookies": "ttwid=1%7C9A286D27vKc5mZtjIupHnDeXatyoXthru3_qe9hop_o%7C1782035248%7Cf3067fb3795e2a40e15cf65689b1a3b74a7cbc2f114772db410be2b4eef481e6; Domain=.tiktok.com; Path=/; Secure; Expires=1813139248; tt_csrf_token=4NOQFKCI-wp-v3R1qmZPgWFl86NGszBk2gp8; Domain=.tiktok.com; Path=/; Secure; tt_chain_token=\"8R9F5Mqm/wLsbHNgs9efgg==\"; Domain=.tiktok.com; Path=/; Secure; Expires=1797587248", "http_headers": {"User-Agent": "Mozilla/5.0 (Windows NT 10.0; Win64; x64) AppleWebKit/537.36 (KHTML, like Gecko) Chrome/147.0.0.0 Safari/537.36", "Accept": "text/html,application/xhtml+xml,application/xml;q=0.9,*/*;q=0.8", "Accept-Language": "en-us,en;q=0.5", "Sec-Fetch-Mode": "navigate", "Referer": "https://www.tiktok.com/@johnnnyhuynh/video/7382967406362103086"}, "format": "bytevc1_1080p_654722-1 - 1080x1920"}], "subtitles": {}, "http_headers": {"User-Agent": "Mozilla/5.0 (Windows NT 10.0; Win64; x64) AppleWebKit/537.36 (KHTML, like Gecko) Chrome/147.0.0.0 Safari/537.36", "Accept": "text/html,application/xhtml+xml,application/xml;q=0.9,*/*;q=0.8", "Accept-Language": "en-us,en;q=0.5", "Sec-Fetch-Mode": "navigate", "Referer": "https://www.tiktok.com/@johnnnyhuynh/video/7382967406362103086"}, "channel": "Johnny Huynh", "channel_id": "MS4wLjABAAAAjb7seXKAGNx7NZXuaD1AiWjZjSDmy39FpZszLA0UdyclOMpyPo7cSH1G1CZk-bWY", "uploader": "johnnnyhuynh", "uploader_id": "6675423808608273414", "channel_url": "https://www.tiktok.com/@MS4wLjABAAAAjb7seXKAGNx7NZXuaD1AiWjZjSDmy39FpZszLA0UdyclOMpyPo7cSH1G1CZk-bWY", "uploader_url": "https://www.tiktok.com/@johnnnyhuynh", "track": "original sound", "artists": ["Johnny Huynh"], "duration": 40, "title": "Tattoo from an empty garage #loreen #tattoo #loreentattoo #fypシ゚viral...", "description": "Tattoo from an empty garage #loreen #tattoo #loreentattoo #fypシ゚viral #viralvideos #sing #singing #coversong ", "timestamp": 1718981059, "view_count": 95500000, "like_count": 11500000, "repost_count": 362400, "comment_count": 102700, "save_count": 1395225, "thumbnails": [{"id": "dynamicCover", "url": "https://p16-common-sign.tiktokcdn-us.com/tos-useast5-p-0068-tx/84dd0c6f54024941b73f977bf02f5986_1718981061~tplv-tiktokx-origin.image?dr=9636&x-expires=1782205200&x-signature=zafXZMkCSC7Qtq6xjq%2Bytj3Qcj0%3D&t=4d5b0474&ps=13740610&shp=81f88b70&shcp=43f4a2f9&idc=useast8", "preference": -2}, {"id": "cover", "url": "https://p16-common-sign.tiktokcdn-us.com/tos-useast5-p-0068-tx/oUTgEQ7B4vB1pingIIkdWBsAZLEj0cRI9iUwY~tplv-tiktokx-origin.image?dr=9636&x-expires=1782205200&x-signature=iL91OO9Nw6HV8XWqlh0hiMCu%2BYU%3D&t=4d5b0474&ps=13740610&shp=81f88b70&shcp=43f4a2f9&idc=useast8", "preference": -1}, {"id": "originCover", "url": "https://p19-common-sign.tiktokcdn-us.com/tos-useast5-p-0068-tx/cd3e79f2b2b04fd783c0a9af8b42fa75_1718981061~tplv-tiktokx-origin.image?dr=9636&x-expires=1782205200&x-signature=J1N5s2NJYoPDqPul1lXVNE6sATY%3D&t=4d5b0474&ps=13740610&shp=81f88b70&shcp=43f4a2f9&idc=useast8", "preference": -1}], "webpage_url": "https://www.tiktok.com/@johnnnyhuynh/video/7382967406362103086", "webpage_url_basename": "7382967406362103086", "webpage_url_domain": "tiktok.com", "extractor": "TikTok", "extractor_key": "TikTok", "thumbnail": "https://p19-common-sign.tiktokcdn-us.com/tos-useast5-p-0068-tx/cd3e79f2b2b04fd783c0a9af8b42fa75_1718981061~tplv-tiktokx-origin.image?dr=9636&x-expires=1782205200&x-signature=J1N5s2NJYoPDqPul1lXVNE6sATY%3D&t=4d5b0474&ps=13740610&shp=81f88b70&shcp=43f4a2f9&idc=useast8", "display_id": "7382967406362103086", "fulltitle": "Tattoo from an empty garage #loreen #tattoo #loreentattoo #fypシ゚viral...", "duration_string": "40", "upload_date": "20240621", "artist": "Johnny Huynh", "epoch": 1782035248, "ext": "mp4", "vcodec": "h265", "acodec": "aac", "format_id": "bytevc1_1080p_654722-1", "tbr": 654, "quality": 3, "preference": -1, "filesize": 3279998, "width": 1080, "height": 1920, "url": "https://v19-webapp-prime.us.tiktok.com/video/tos/useast5/tos-useast5-ve-0068c001-tx/oQDiAUEQ0IBwRk4gQIn0gpNxv7AsWgYBs1ZEi/?a=1988&bti=ODszNWYuMDE6&&bt=639&ft=4KJMyMzm8Zmo06ebha4jVczjQpWrKsd.&mime_type=video_mp4&rc=OzxkOzU4OzdoZ2k3ZDtpNkBpM2ppZG45cjNzczMzZzczNEAxNF5gL2E2NTMxXzRfLl82YSNqLWNgMmRrMG5gLS1kMS9zcw%3D%3D&expire=1782208088&l=2026062109472840F92B237B7DD5D01BE3&ply_type=2&policy=2&signature=ffc17677882e9d38363df6fcf4241d84&tk=tt_chain_token&btag=e00088000", "protocol": "https", "video_ext": "mp4", "audio_ext": "none", "resolution": "1080x1920", "dynamic_range": "SDR", "aspect_ratio": 0.56, "cookies": "ttwid=1%7C9A286D27vKc5mZtjIupHnDeXatyoXthru3_qe9hop_o%7C1782035248%7Cf3067fb3795e2a40e15cf65689b1a3b74a7cbc2f114772db410be2b4eef481e6; Domain=.tiktok.com; Path=/; Secure; Expires=1813139248; tt_csrf_token=4NOQFKCI-wp-v3R1qmZPgWFl86NGszBk2gp8; Domain=.tiktok.com; Path=/; Secure; tt_chain_token=\"8R9F5Mqm/wLsbHNgs9efgg==\"; Domain=.tiktok.com; Path=/; Secure; Expires=1797587248", "format": "bytevc1_1080p_654722-1 - 1080x1920", "_type": "video", "_version": {"version": "2026.06.09", "release_git_head": "821bef0f00178916d60dbc86bc0bcb8cc3bae8d5", "repository": "yt-dlp/yt-dlp"}}