{"id": "7288808722774641953", "formats": [{"ext": "mp4", "vcodec": "h264", "acodec": "aac", "format_id": "download", "url": "https://v16-webapp-prime.us.tiktok.com/video/tos/no1a/tos-no1a-ve-37c710-no/oELenIYEBrv3NAdYoiP5AmQ3ti5sCyhBuyhK7j/?a=1988&bti=ODszNWYuMDE6&&bt=1752&ft=4KJMyMzm8Zmo0aGlBa4jVK_bQpWrKsd.&mime_type=video_mp4&rc=cnF8b2hsc2d3SkBwaHIxaDFybndmNzU1Mzs6NGY2OTU3O2RkO0BpanJodWw5cnJxcTMzZjgzM0BjRl5Nc3FePmJKYSNvYF90aHFmOiMxNTNgNWJgXmMxYy8uMjYzYSNkbjJwMmQ0YmVgLS1kL2Nzcw%3D%3D&expire=1782903285&l=202606291054324DD979BD0D57EBF3EA94&ply_type=2&policy=2&signature=519577280a531537ac364fecfb6b5a15&tk=tt_chain_token&btag=e000b0000", "format_note": "watermarked", "preference": -2, "protocol": "https", "video_ext": "mp4", "audio_ext": "none", "dynamic_range": "SDR", "cookies": "ttwid=1%7CjiasJqFBuiTAIbCYLSVfyVX_Y4itEYv53QGBguw1VBM%7C1782730472%7C89ba7039583c6266be545456c7a8bfa6947bb19a5472aaedc58ec16fb11ca765; Domain=.tiktok.com; Path=/; Secure; Expires=1813834472; tt_csrf_token=LCLKik7F-jwY7NZR_b4mXZ7VVHec6wIj_teU; Domain=.tiktok.com; Path=/; Secure; tt_chain_token=\"qeF8C2X/BAJRgKmSiPjV7A==\"; Domain=.tiktok.com; Path=/; Secure; Expires=1798282472", "http_headers": {"User-Agent": "Mozilla/5.0 (Windows NT 10.0; Win64; x64) AppleWebKit/537.36 (KHTML, like Gecko) Chrome/149.0.0.0 Safari/537.36", "Accept": "text/html,application/xhtml+xml,application/xml;q=0.9,*/*;q=0.8", "Accept-Language": "en-us,en;q=0.5", "Sec-Fetch-Mode": "navigate", "Referer": "https://www.tiktok.com/@wzrse/video/7288808722774641953"}, "format": "download - unknown (watermarked)"}, {"ext": "mp4", "vcodec": "h264", "acodec": "aac", "format_id": "h264_540p_906048-0", "tbr": 906, "quality": 1, "preference": -1, "filesize": 1517632, "width": 576, "height": 1024, "url": "https://v16-webapp-prime.us.tiktok.com/video/tos/useast2a/tos-useast2a-ve-68c810-euttp/oMrInEdDoA31h5yYKiPsNyBA5BechiBt2crYQj/?a=1988&bti=ODszNWYuMDE6&&bt=884&ft=4KJMyMzm8Zmo0aGlBa4jVK_bQpWrKsd.&mime_type=video_mp4&rc=NWQ0OjY0OTlnM2VpNDZmO0BpanJodWw5cnJxcTMzZjgzM0A1XjReNF40XjQxX2MzYC0xYSNkbjJwMmQ0YmVgLS1kL2Nzcw%3D%3D&expire=1782903285&l=202606291054324DD979BD0D57EBF3EA94&ply_type=2&policy=2&signature=de75f1d6a7632adb958e25593141c67e&tk=tt_chain_token&btag=e000b0000", "protocol": "https", "video_ext": "mp4", "audio_ext": "none", "resolution": "576x1024", "dynamic_range": "SDR", "aspect_ratio": 0.56, "cookies": "ttwid=1%7CjiasJqFBuiTAIbCYLSVfyVX_Y4itEYv53QGBguw1VBM%7C1782730472%7C89ba7039583c6266be545456c7a8bfa6947bb19a5472aaedc58ec16fb11ca765; Domain=.tiktok.com; Path=/; Secure; Expires=1813834472; tt_csrf_token=LCLKik7F-jwY7NZR_b4mXZ7VVHec6wIj_teU; Domain=.tiktok.com; Path=/; Secure; tt_chain_token=\"qeF8C2X/BAJRgKmSiPjV7A==\"; Domain=.tiktok.com; Path=/; Secure; Expires=1798282472", "http_headers": {"User-Agent": "Mozilla/5.0 (Windows NT 10.0; Win64; x64) AppleWebKit/537.36 (KHTML, like Gecko) Chrome/149.0.0.0 Safari/537.36", "Accept": "text/html,application/xhtml+xml,application/xml;q=0.9,*/*;q=0.8", "Accept-Language": "en-us,en;q=0.5", "Sec-Fetch-Mode": "navigate", "Referer": "https://www.tiktok.com/@wzrse/video/7288808722774641953"}, "format": "h264_540p_906048-0 - 576x1024"}, {"ext": "mp4", "vcodec": "h264", "acodec": "aac", "format_id": "h264_540p_906048-1", "tbr": 906, "quality": 1, "preference": -1, "filesize": 1517632, "width": 576, "height": 1024, "url": "https://v19-webapp-prime.us.tiktok.com/video/tos/useast2a/tos-useast2a-ve-68c810-euttp/oMrInEdDoA31h5yYKiPsNyBA5BechiBt2crYQj/?a=1988&bti=ODszNWYuMDE6&&bt=884&ft=4KJMyMzm8Zmo0aGlBa4jVK_bQpWrKsd.&mime_type=video_mp4&rc=NWQ0OjY0OTlnM2VpNDZmO0BpanJodWw5cnJxcTMzZjgzM0A1XjReNF40XjQxX2MzYC0xYSNkbjJwMmQ0YmVgLS1kL2Nzcw%3D%3D&expire=1782903285&l=202606291054324DD979BD0D57EBF3EA94&ply_type=2&policy=2&signature=de75f1d6a7632adb958e25593141c67e&tk=tt_chain_token&btag=e000b0000", "protocol": "https", "video_ext": "mp4", "audio_ext": "none", "resolution": "576x1024", "dynamic_range": "SDR", "aspect_ratio": 0.56, "cookies": "ttwid=1%7CjiasJqFBuiTAIbCYLSVfyVX_Y4itEYv53QGBguw1VBM%7C1782730472%7C89ba7039583c6266be545456c7a8bfa6947bb19a5472aaedc58ec16fb11ca765; Domain=.tiktok.com; Path=/; Secure; Expires=1813834472; tt_csrf_token=LCLKik7F-jwY7NZR_b4mXZ7VVHec6wIj_teU; Domain=.tiktok.com; Path=/; Secure; tt_chain_token=\"qeF8C2X/BAJRgKmSiPjV7A==\"; Domain=.tiktok.com; Path=/; Secure; Expires=1798282472", "http_headers": {"User-Agent": "Mozilla/5.0 (Windows NT 10.0; Win64; x64) AppleWebKit/537.36 (KHTML, like Gecko) Chrome/149.0.0.0 Safari/537.36", "Accept": "text/html,application/xhtml+xml,application/xml;q=0.9,*/*;q=0.8", "Accept-Language": "en-us,en;q=0.5", "Sec-Fetch-Mode": "navigate", "Referer": "https://www.tiktok.com/@wzrse/video/7288808722774641953"}, "format": "h264_540p_906048-1 - 576x1024"}, {"ext": "mp4", "vcodec": "h264", "acodec": "aac", "format_id": "h264_540p_1611337-0", "tbr": 1611, "quality": 1, "preference": -1, "filesize": 2698990, "width": 576, "height": 1024, "url": "https://v16-webapp-prime.us.tiktok.com/video/tos/useast2a/tos-useast2a-ve-68c810-euttp/o0CkY2iEIhoyYwePsdinj2vth23r6BA5BANKQy/?a=1988&bti=ODszNWYuMDE6&&bt=1573&ft=4KJMyMzm8Zmo0aGlBa4jVK_bQpWrKsd.&mime_type=video_mp4&rc=PDw3ZmQzOmk5NTU5Ozc4NEBpanJodWw5cnJxcTMzZjgzM0A0YzVgMTYwXy8xLTY0XjRgYSNkbjJwMmQ0YmVgLS1kL2Nzcw%3D%3D&expire=1782903285&l=202606291054324DD979BD0D57EBF3EA94&ply_type=2&policy=2&signature=65e948bedfb5d71b48146baeda81f739&tk=tt_chain_token&btag=e000b0000", "protocol": "https", "video_ext": "mp4", "audio_ext": "none", "resolution": "576x1024", "dynamic_range": "SDR", "aspect_ratio": 0.56, "cookies": "ttwid=1%7CjiasJqFBuiTAIbCYLSVfyVX_Y4itEYv53QGBguw1VBM%7C1782730472%7C89ba7039583c6266be545456c7a8bfa6947bb19a5472aaedc58ec16fb11ca765; Domain=.tiktok.com; Path=/; Secure; Expires=1813834472; tt_csrf_token=LCLKik7F-jwY7NZR_b4mXZ7VVHec6wIj_teU; Domain=.tiktok.com; Path=/; Secure; tt_chain_token=\"qeF8C2X/BAJRgKmSiPjV7A==\"; Domain=.tiktok.com; Path=/; Secure; Expires=1798282472", "http_headers": {"User-Agent": "Mozilla/5.0 (Windows NT 10.0; Win64; x64) AppleWebKit/537.36 (KHTML, like Gecko) Chrome/149.0.0.0 Safari/537.36", "Accept": "text/html,application/xhtml+xml,application/xml;q=0.9,*/*;q=0.8", "Accept-Language": "en-us,en;q=0.5", "Sec-Fetch-Mode": "navigate", "Referer": "https://www.tiktok.com/@wzrse/video/7288808722774641953"}, "format": "h264_540p_1611337-0 - 576x1024"}, {"ext": "mp4", "vcodec": "h264", "acodec": "aac", "format_id": "h264_540p_1611337-1", "tbr": 1611, "quality": 1, "preference": -1, "filesize": 2698990, "width": 576, "height": 1024, "url": "https://v19-webapp-prime.us.tiktok.com/video/tos/useast2a/tos-useast2a-ve-68c810-euttp/o0CkY2iEIhoyYwePsdinj2vth23r6BA5BANKQy/?a=1988&bti=ODszNWYuMDE6&&bt=1573&ft=4KJMyMzm8Zmo0aGlBa4jVK_bQpWrKsd.&mime_type=video_mp4&rc=PDw3ZmQzOmk5NTU5Ozc4NEBpanJodWw5cnJxcTMzZjgzM0A0YzVgMTYwXy8xLTY0XjRgYSNkbjJwMmQ0YmVgLS1kL2Nzcw%3D%3D&expire=1782903285&l=202606291054324DD979BD0D57EBF3EA94&ply_type=2&policy=2&signature=65e948bedfb5d71b48146baeda81f739&tk=tt_chain_token&btag=e000b0000", "protocol": "https", "video_ext": "mp4", "audio_ext": "none", "resolution": "576x1024", "dynamic_range": "SDR", "aspect_ratio": 0.56, "cookies": "ttwid=1%7CjiasJqFBuiTAIbCYLSVfyVX_Y4itEYv53QGBguw1VBM%7C1782730472%7C89ba7039583c6266be545456c7a8bfa6947bb19a5472aaedc58ec16fb11ca765; Domain=.tiktok.com; Path=/; Secure; Expires=1813834472; tt_csrf_token=LCLKik7F-jwY7NZR_b4mXZ7VVHec6wIj_teU; Domain=.tiktok.com; Path=/; Secure; tt_chain_token=\"qeF8C2X/BAJRgKmSiPjV7A==\"; Domain=.tiktok.com; Path=/; Secure; Expires=1798282472", "http_headers": {"User-Agent": "Mozilla/5.0 (Windows NT 10.0; Win64; x64) AppleWebKit/537.36 (KHTML, like Gecko) Chrome/149.0.0.0 Safari/537.36", "Accept": "text/html,application/xhtml+xml,application/xml;q=0.9,*/*;q=0.8", "Accept-Language": "en-us,en;q=0.5", "Sec-Fetch-Mode": "navigate", "Referer": "https://www.tiktok.com/@wzrse/video/7288808722774641953"}, "format": "h264_540p_1611337-1 - 576x1024"}], "subtitles": {}, "http_headers": {"User-Agent": "Mozilla/5.0 (Windows NT 10.0; Win64; x64) AppleWebKit/537.36 (KHTML, like Gecko) Chrome/149.0.0.0 Safari/537.36", "Accept": "text/html,application/xhtml+xml,application/xml;q=0.9,*/*;q=0.8", "Accept-Language": "en-us,en;q=0.5", "Sec-Fetch-Mode": "navigate", "Referer": "https://www.tiktok.com/@wzrse/video/7288808722774641953"}, "channel": "wzrse", "channel_id": "MS4wLjABAAAAcjohPe8AJWZPLdnCXmfII3Ui6i2YXg5yHG1EIYZhdrYwKZ97rsWHCkwoaMVRyx8G", "uploader": "wzrse", "uploader_id": "7048665029352113158", "channel_url": "https://www.tiktok.com/@MS4wLjABAAAAcjohPe8AJWZPLdnCXmfII3Ui6i2YXg5yHG1EIYZhdrYwKZ97rsWHCkwoaMVRyx8G", "uploader_url": "https://www.tiktok.com/@wzrse", "track": "LORD WAD SOUND", "artists": ["💤"], "duration": 13, "title": "Fancy ❤️‍🔥 #fyp #viral #edit #quality ", "description": "Fancy ❤️‍🔥 #fyp #viral #edit #quality ", "timestamp": 1697058031, "view_count": 21200000, "like_count": 3300000, "repost_count": 64900, "comment_count": 6388, "save_count": 532384, "thumbnails": [{"id": "dynamicCover", "url": "https://p19-common-sign.tiktokcdn-us.com/tos-useast2a-p-0037-euttp/df6fdbf5f2bf4badbf2898684d56d04b_1709406058~tplv-tiktokx-origin.image?dr=9636&x-expires=1782900000&x-signature=ArIDzKasU0QTtMQQ8nVpqLd1NMI%3D&t=4d5b0474&ps=13740610&shp=81f88b70&shcp=43f4a2f9&idc=useast8", "preference": -2}, {"id": "cover", "url": "https://p19-common-sign.tiktokcdn-us.com/tos-useast2a-p-0037-euttp/oQs2jAtGNnBGriIyreiPhAonYdRc3hE5KXByBY~tplv-tiktokx-origin.image?dr=9636&x-expires=1782900000&x-signature=wreHpDPYCUqyIUUxotElcmTAaII%3D&t=4d5b0474&ps=13740610&shp=81f88b70&shcp=43f4a2f9&idc=useast8", "preference": -1}, {"id": "originCover", "url": "https://p16-common-sign.tiktokcdn-us.com/tos-useast2a-p-0037-euttp/8b7d82c78227452986cfe0ee1bb061aa_1709406059~tplv-tiktokx-origin.image?dr=9636&x-expires=1782900000&x-signature=vFxka7ObCtDJtHYh38GTjjhQgYc%3D&t=4d5b0474&ps=13740610&shp=81f88b70&shcp=43f4a2f9&idc=useast8", "preference": -1}], "webpage_url": "https://www.tiktok.com/@wzrse/video/7288808722774641953", "webpage_url_basename": "7288808722774641953", "webpage_url_domain": "tiktok.com", "extractor": "TikTok", "extractor_key": "TikTok", "thumbnail": "https://p16-common-sign.tiktokcdn-us.com/tos-useast2a-p-0037-euttp/8b7d82c78227452986cfe0ee1bb061aa_1709406059~tplv-tiktokx-origin.image?dr=9636&x-expires=1782900000&x-signature=vFxka7ObCtDJtHYh38GTjjhQgYc%3D&t=4d5b0474&ps=13740610&shp=81f88b70&shcp=43f4a2f9&idc=useast8", "display_id": "7288808722774641953", "fulltitle": "Fancy ❤️‍🔥 #fyp #viral #edit #quality ", "duration_string": "13", "upload_date": "20231011", "artist": "💤", "epoch": 1782730472, "ext": "mp4", "vcodec": "h264", "acodec": "aac", "format_id": "h264_540p_1611337-1", "tbr": 1611, "quality": 1, "preference": -1, "filesize": 2698990, "width": 576, "height": 1024, "url": "https://v19-webapp-prime.us.tiktok.com/video/tos/useast2a/tos-useast2a-ve-68c810-euttp/o0CkY2iEIhoyYwePsdinj2vth23r6BA5BANKQy/?a=1988&bti=ODszNWYuMDE6&&bt=1573&ft=4KJMyMzm8Zmo0aGlBa4jVK_bQpWrKsd.&mime_type=video_mp4&rc=PDw3ZmQzOmk5NTU5Ozc4NEBpanJodWw5cnJxcTMzZjgzM0A0YzVgMTYwXy8xLTY0XjRgYSNkbjJwMmQ0YmVgLS1kL2Nzcw%3D%3D&expire=1782903285&l=202606291054324DD979BD0D57EBF3EA94&ply_type=2&policy=2&signature=65e948bedfb5d71b48146baeda81f739&tk=tt_chain_token&btag=e000b0000", "protocol": "https", "video_ext": "mp4", "audio_ext": "none", "resolution": "576x1024", "dynamic_range": "SDR", "aspect_ratio": 0.56, "cookies": "ttwid=1%7CjiasJqFBuiTAIbCYLSVfyVX_Y4itEYv53QGBguw1VBM%7C1782730472%7C89ba7039583c6266be545456c7a8bfa6947bb19a5472aaedc58ec16fb11ca765; Domain=.tiktok.com; Path=/; Secure; Expires=1813834472; tt_csrf_token=LCLKik7F-jwY7NZR_b4mXZ7VVHec6wIj_teU; Domain=.tiktok.com; Path=/; Secure; tt_chain_token=\"qeF8C2X/BAJRgKmSiPjV7A==\"; Domain=.tiktok.com; Path=/; Secure; Expires=1798282472", "format": "h264_540p_1611337-1 - 576x1024", "_type": "video", "_version": {"version": "2026.06.09", "release_git_head": "821bef0f00178916d60dbc86bc0bcb8cc3bae8d5", "repository": "yt-dlp/yt-dlp"}}